{"Success":1,"Results":{"COLUMNS":["ALLOWEDDROPCODE","ALLOWEDDROPDESC","CONSENTOFINSRUCTORREQUIRED","COURSE_NUMBER","CREDIT_HOURS_HIGH","CREDIT_HOURS_LOW","UNITS_HIGH","UNITS_LOW","UNITS_IND","DESCRIPTION","DSPCRN","FINALEXAMSTARTDATE","DROP_DATE","GE2CREDIT","GE3CREDIT","GRADE_MODE_CHOICES","GRADE_MODES_POSSIBLE","GRADE_MODE_CODE","ISVARIABLEUNIT","PASSEDCRN","PREREQUISITES","SEC","SUBJECT_CODE","TITLE","TITLE_SHORT","COURSEMATERIALSTERM","COURSEMEETINGDATA","INSTRUCTORS","COURSEDEPTSPECIFICNOTESDATA","COURSESUBJECTSPECIFICNOTESDATA","COURSESPECIFICNOTESDATA","CROSS_LISTING","CREDIT_LIMITATION","BLEND_SEATS_AVAIL","BLEND_WAIT_COUNT","RECORDNUM"],"DATA":[["R","20 Day Drop",0,"203",0,4,0,4,null,"Focuses on the preparation of complex financial statements. Topics include accounting recognition, measurement, and disclosure, as well as the theoretical foundations of and motivations for financial reporting choices.","20825",null,"February, 04 2019 00:00:00","","","","",null,0,"20825","ACC 201 or (MGT 200A or MGP 200A or MGB 200A)","001","ACC","Intmd Financial Report","Intmd Financial Report","Winter 19","{\"QUERY\":{\"COLUMNS\":[\"BLDG_DESC\",\"ROOM\",\"BEGIN_TIME\",\"END_TIME\",\"START_DATE\",\"END_DATE\",\"MEET_TYPE_CODE\",\"MEET_TYPE_DESC\",\"MEET_TYPE_DESC_SHORT\",\"SUNDAY\",\"MONDAY\",\"TUESDAY\",\"WEDNESDAY\",\"THURSDAY\",\"FRIDAY\",\"SATURDAY\",\"WEEKDAYS\",\"MEET_CATEGORY\"],\"DATA\":[[\"Gallagher Hall\",\"1213\",\"1410\",\"1800\",\"January, 07 2019 00:00:00\",\"March, 15 2019 00:00:00\",\"A\",\"Lecture\",\"LEC\",null,null,\"T\",null,null,null,null,\"T\",\"01\"]]},\"QUERY_METADATA\":[{\"TypeName\":\"VARCHAR\",\"IsCaseSensitive\":true,\"Name\":\"bldg_desc\"},{\"TypeName\":\"VARCHAR\",\"IsCaseSensitive\":true,\"Name\":\"ROOM\"},{\"TypeName\":\"VARCHAR\",\"IsCaseSensitive\":true,\"Name\":\"begin_time\"},{\"TypeName\":\"VARCHAR\",\"IsCaseSensitive\":true,\"Name\":\"end_time\"},{\"TypeName\":\"TIMESTAMP\",\"IsCaseSensitive\":false,\"Name\":\"start_date\"},{\"TypeName\":\"TIMESTAMP\",\"IsCaseSensitive\":false,\"Name\":\"end_date\"},{\"TypeName\":\"VARCHAR\",\"IsCaseSensitive\":true,\"Name\":\"meet_type_code\"},{\"TypeName\":\"VARCHAR\",\"IsCaseSensitive\":true,\"Name\":\"meet_type_desc\"},{\"TypeName\":\"VARCHAR\",\"IsCaseSensitive\":true,\"Name\":\"meet_type_desc_short\"},{\"TypeName\":\"VARCHAR\",\"IsCaseSensitive\":true,\"Name\":\"sunday\"},{\"TypeName\":\"VARCHAR\",\"IsCaseSensitive\":true,\"Name\":\"monday\"},{\"TypeName\":\"VARCHAR\",\"IsCaseSensitive\":true,\"Name\":\"tuesday\"},{\"TypeName\":\"VARCHAR\",\"IsCaseSensitive\":true,\"Name\":\"wednesday\"},{\"TypeName\":\"VARCHAR\",\"IsCaseSensitive\":true,\"Name\":\"thursday\"},{\"TypeName\":\"VARCHAR\",\"IsCaseSensitive\":true,\"Name\":\"friday\"},{\"TypeName\":\"VARCHAR\",\"IsCaseSensitive\":true,\"Name\":\"saturday\"},{\"TypeName\":\"VARCHAR\",\"IsCaseSensitive\":false,\"Name\":\"WEEKDAYS\"},{\"TypeName\":\"VARCHAR\",\"IsCaseSensitive\":true,\"Name\":\"meet_category\"}]}","{\"QUERY\":{\"COLUMNS\":[\"EMAIL\",\"FIRST_NAME\",\"LAST_NAME\",\"MIDDLE_NAME\",\"CATEGORY\",\"PRIMARY_IND\"],\"DATA\":[[\"panwong@ucdavis.edu\",\"Paul\",\"Wong\",\"A\",\"01\",\"Y\"]]},\"QUERY_METADATA\":[{\"TypeName\":\"VARCHAR\",\"IsCaseSensitive\":true,\"Name\":\"email\"},{\"TypeName\":\"VARCHAR\",\"IsCaseSensitive\":true,\"Name\":\"first_name\"},{\"TypeName\":\"VARCHAR\",\"IsCaseSensitive\":true,\"Name\":\"last_name\"},{\"TypeName\":\"VARCHAR\",\"IsCaseSensitive\":true,\"Name\":\"middle_name\"},{\"TypeName\":\"VARCHAR\",\"IsCaseSensitive\":true,\"Name\":\"category\"},{\"TypeName\":\"VARCHAR\",\"IsCaseSensitive\":true,\"Name\":\"primary_ind\"}]}","","{\"QUERY\":{\"COLUMNS\":[\"SCRTEXT_SUBJ_CODE\",\"SCRTEXT_CRSE_NUMB\",\"SCRTEXT_EFF_TERM\",\"SCRTEXT_TEXT_CODE\",\"SCRTEXT_SEQNO\",\"SCRTEXT_TEXT\"],\"DATA\":[[\"ACC\",\"203\",\"201801\",\"A\",1.00000000000000000000,\"** OPEN TO STUDENTS ENROLLED IN THE MPAC PROGRAM (GPAC) **\"]]},\"QUERY_METADATA\":[{\"TypeName\":\"VARCHAR\",\"IsCaseSensitive\":true,\"Name\":\"SCRTEXT_SUBJ_CODE\"},{\"TypeName\":\"VARCHAR\",\"IsCaseSensitive\":true,\"Name\":\"SCRTEXT_CRSE_NUMB\"},{\"TypeName\":\"VARCHAR\",\"IsCaseSensitive\":true,\"Name\":\"SCRTEXT_EFF_TERM\"},{\"TypeName\":\"VARCHAR\",\"IsCaseSensitive\":true,\"Name\":\"SCRTEXT_TEXT_CODE\"},{\"TypeName\":\"DECIMAL\",\"IsCaseSensitive\":false,\"Name\":\"SCRTEXT_SEQNO\"},{\"TypeName\":\"VARCHAR\",\"IsCaseSensitive\":true,\"Name\":\"SCRTEXT_TEXT\"}]}","",null,"Not open for credit to students who have taken any MGT 200A.",7,0,1],["R","20 Day Drop",0,"213",0,4,0,4,null,"Detailed analysis of federal taxation of individuals. Topics include the timing of income recognition, deductions and credits for tax purposes, as well as the basics of property transactions.","20826",null,"February, 04 2019 00:00:00","","","","",null,0,"20826","ACC 211;  (MGT 264 or MGP 264 or MGB 264)","001","ACC","Intmd Tax Report","Intmd Tax Report","Winter 19","{\"QUERY\":{\"COLUMNS\":[\"BLDG_DESC\",\"ROOM\",\"BEGIN_TIME\",\"END_TIME\",\"START_DATE\",\"END_DATE\",\"MEET_TYPE_CODE\",\"MEET_TYPE_DESC\",\"MEET_TYPE_DESC_SHORT\",\"SUNDAY\",\"MONDAY\",\"TUESDAY\",\"WEDNESDAY\",\"THURSDAY\",\"FRIDAY\",\"SATURDAY\",\"WEEKDAYS\",\"MEET_CATEGORY\"],\"DATA\":[[\"Gallagher Hall\",\"1213\",\"1210\",\"1600\",\"January, 07 2019 00:00:00\",\"March, 15 2019 00:00:00\",\"A\",\"Lecture\",\"LEC\",null,null,null,null,\"R\",null,null,\"R\",\"01\"]]},\"QUERY_METADATA\":[{\"TypeName\":\"VARCHAR\",\"IsCaseSensitive\":true,\"Name\":\"bldg_desc\"},{\"TypeName\":\"VARCHAR\",\"IsCaseSensitive\":true,\"Name\":\"ROOM\"},{\"TypeName\":\"VARCHAR\",\"IsCaseSensitive\":true,\"Name\":\"begin_time\"},{\"TypeName\":\"VARCHAR\",\"IsCaseSensitive\":true,\"Name\":\"end_time\"},{\"TypeName\":\"TIMESTAMP\",\"IsCaseSensitive\":false,\"Name\":\"start_date\"},{\"TypeName\":\"TIMESTAMP\",\"IsCaseSensitive\":false,\"Name\":\"end_date\"},{\"TypeName\":\"VARCHAR\",\"IsCaseSensitive\":true,\"Name\":\"meet_type_code\"},{\"TypeName\":\"VARCHAR\",\"IsCaseSensitive\":true,\"Name\":\"meet_type_desc\"},{\"TypeName\":\"VARCHAR\",\"IsCaseSensitive\":true,\"Name\":\"meet_type_desc_short\"},{\"TypeName\":\"VARCHAR\",\"IsCaseSensitive\":true,\"Name\":\"sunday\"},{\"TypeName\":\"VARCHAR\",\"IsCaseSensitive\":true,\"Name\":\"monday\"},{\"TypeName\":\"VARCHAR\",\"IsCaseSensitive\":true,\"Name\":\"tuesday\"},{\"TypeName\":\"VARCHAR\",\"IsCaseSensitive\":true,\"Name\":\"wednesday\"},{\"TypeName\":\"VARCHAR\",\"IsCaseSensitive\":true,\"Name\":\"thursday\"},{\"TypeName\":\"VARCHAR\",\"IsCaseSensitive\":true,\"Name\":\"friday\"},{\"TypeName\":\"VARCHAR\",\"IsCaseSensitive\":true,\"Name\":\"saturday\"},{\"TypeName\":\"VARCHAR\",\"IsCaseSensitive\":false,\"Name\":\"WEEKDAYS\"},{\"TypeName\":\"VARCHAR\",\"IsCaseSensitive\":true,\"Name\":\"meet_category\"}]}","{\"QUERY\":{\"COLUMNS\":[\"EMAIL\",\"FIRST_NAME\",\"LAST_NAME\",\"MIDDLE_NAME\",\"CATEGORY\",\"PRIMARY_IND\"],\"DATA\":[[\"wsnyder@ucdavis.edu\",\"Willard\",\"Snyder\",null,\"01\",\"Y\"]]},\"QUERY_METADATA\":[{\"TypeName\":\"VARCHAR\",\"IsCaseSensitive\":true,\"Name\":\"email\"},{\"TypeName\":\"VARCHAR\",\"IsCaseSensitive\":true,\"Name\":\"first_name\"},{\"TypeName\":\"VARCHAR\",\"IsCaseSensitive\":true,\"Name\":\"last_name\"},{\"TypeName\":\"VARCHAR\",\"IsCaseSensitive\":true,\"Name\":\"middle_name\"},{\"TypeName\":\"VARCHAR\",\"IsCaseSensitive\":true,\"Name\":\"category\"},{\"TypeName\":\"VARCHAR\",\"IsCaseSensitive\":true,\"Name\":\"primary_ind\"}]}","","{\"QUERY\":{\"COLUMNS\":[\"SCRTEXT_SUBJ_CODE\",\"SCRTEXT_CRSE_NUMB\",\"SCRTEXT_EFF_TERM\",\"SCRTEXT_TEXT_CODE\",\"SCRTEXT_SEQNO\",\"SCRTEXT_TEXT\"],\"DATA\":[[\"ACC\",\"213\",\"201801\",\"A\",1.00000000000000000000,\"** OPEN TO STUDENTS ENROLLED IN THE MPAC PROGRAM (GPAC) **\"]]},\"QUERY_METADATA\":[{\"TypeName\":\"VARCHAR\",\"IsCaseSensitive\":true,\"Name\":\"SCRTEXT_SUBJ_CODE\"},{\"TypeName\":\"VARCHAR\",\"IsCaseSensitive\":true,\"Name\":\"SCRTEXT_CRSE_NUMB\"},{\"TypeName\":\"VARCHAR\",\"IsCaseSensitive\":true,\"Name\":\"SCRTEXT_EFF_TERM\"},{\"TypeName\":\"VARCHAR\",\"IsCaseSensitive\":true,\"Name\":\"SCRTEXT_TEXT_CODE\"},{\"TypeName\":\"DECIMAL\",\"IsCaseSensitive\":false,\"Name\":\"SCRTEXT_SEQNO\"},{\"TypeName\":\"VARCHAR\",\"IsCaseSensitive\":true,\"Name\":\"SCRTEXT_TEXT\"}]}","",null,null,1,0,2],["R","20 Day Drop",0,"251",0,4,0,4,null,"Analysis of management accounting systems including cost accounting, performance measurement, and compensation and reward systems. Focuses on the production of information useful for managerial decision-making, as well as the design of these systems.","20828",null,"February, 04 2019 00:00:00","","","","",null,0,"20828","ACC 201;  (MGT 200A or MGP 200A or MGB 200A)","001","ACC","Managerial Acct & Ctrls","Managerial Acct & Ctrls","Winter 19","{\"QUERY\":{\"COLUMNS\":[\"BLDG_DESC\",\"ROOM\",\"BEGIN_TIME\",\"END_TIME\",\"START_DATE\",\"END_DATE\",\"MEET_TYPE_CODE\",\"MEET_TYPE_DESC\",\"MEET_TYPE_DESC_SHORT\",\"SUNDAY\",\"MONDAY\",\"TUESDAY\",\"WEDNESDAY\",\"THURSDAY\",\"FRIDAY\",\"SATURDAY\",\"WEEKDAYS\",\"MEET_CATEGORY\"],\"DATA\":[[\"Gallagher Hall\",\"1213\",\"1210\",\"1600\",\"January, 07 2019 00:00:00\",\"March, 15 2019 00:00:00\",\"A\",\"Lecture\",\"LEC\",null,\"M\",null,null,null,null,null,\"M\",\"01\"]]},\"QUERY_METADATA\":[{\"TypeName\":\"VARCHAR\",\"IsCaseSensitive\":true,\"Name\":\"bldg_desc\"},{\"TypeName\":\"VARCHAR\",\"IsCaseSensitive\":true,\"Name\":\"ROOM\"},{\"TypeName\":\"VARCHAR\",\"IsCaseSensitive\":true,\"Name\":\"begin_time\"},{\"TypeName\":\"VARCHAR\",\"IsCaseSensitive\":true,\"Name\":\"end_time\"},{\"TypeName\":\"TIMESTAMP\",\"IsCaseSensitive\":false,\"Name\":\"start_date\"},{\"TypeName\":\"TIMESTAMP\",\"IsCaseSensitive\":false,\"Name\":\"end_date\"},{\"TypeName\":\"VARCHAR\",\"IsCaseSensitive\":true,\"Name\":\"meet_type_code\"},{\"TypeName\":\"VARCHAR\",\"IsCaseSensitive\":true,\"Name\":\"meet_type_desc\"},{\"TypeName\":\"VARCHAR\",\"IsCaseSensitive\":true,\"Name\":\"meet_type_desc_short\"},{\"TypeName\":\"VARCHAR\",\"IsCaseSensitive\":true,\"Name\":\"sunday\"},{\"TypeName\":\"VARCHAR\",\"IsCaseSensitive\":true,\"Name\":\"monday\"},{\"TypeName\":\"VARCHAR\",\"IsCaseSensitive\":true,\"Name\":\"tuesday\"},{\"TypeName\":\"VARCHAR\",\"IsCaseSensitive\":true,\"Name\":\"wednesday\"},{\"TypeName\":\"VARCHAR\",\"IsCaseSensitive\":true,\"Name\":\"thursday\"},{\"TypeName\":\"VARCHAR\",\"IsCaseSensitive\":true,\"Name\":\"friday\"},{\"TypeName\":\"VARCHAR\",\"IsCaseSensitive\":true,\"Name\":\"saturday\"},{\"TypeName\":\"VARCHAR\",\"IsCaseSensitive\":false,\"Name\":\"WEEKDAYS\"},{\"TypeName\":\"VARCHAR\",\"IsCaseSensitive\":true,\"Name\":\"meet_category\"}]}","{\"QUERY\":{\"COLUMNS\":[\"EMAIL\",\"FIRST_NAME\",\"LAST_NAME\",\"MIDDLE_NAME\",\"CATEGORY\",\"PRIMARY_IND\"],\"DATA\":[[\"swanderson@ucdavis.edu\",\"Shannon\",\"Anderson\",\"W\",\"01\",\"Y\"]]},\"QUERY_METADATA\":[{\"TypeName\":\"VARCHAR\",\"IsCaseSensitive\":true,\"Name\":\"email\"},{\"TypeName\":\"VARCHAR\",\"IsCaseSensitive\":true,\"Name\":\"first_name\"},{\"TypeName\":\"VARCHAR\",\"IsCaseSensitive\":true,\"Name\":\"last_name\"},{\"TypeName\":\"VARCHAR\",\"IsCaseSensitive\":true,\"Name\":\"middle_name\"},{\"TypeName\":\"VARCHAR\",\"IsCaseSensitive\":true,\"Name\":\"category\"},{\"TypeName\":\"VARCHAR\",\"IsCaseSensitive\":true,\"Name\":\"primary_ind\"}]}","","{\"QUERY\":{\"COLUMNS\":[\"SCRTEXT_SUBJ_CODE\",\"SCRTEXT_CRSE_NUMB\",\"SCRTEXT_EFF_TERM\",\"SCRTEXT_TEXT_CODE\",\"SCRTEXT_SEQNO\",\"SCRTEXT_TEXT\"],\"DATA\":[[\"ACC\",\"251\",\"201801\",\"A\",1.00000000000000000000,\"** OPEN TO STUDENTS ENROLLED IN THE MPAC PROGRAM (GPAC) **\"]]},\"QUERY_METADATA\":[{\"TypeName\":\"VARCHAR\",\"IsCaseSensitive\":true,\"Name\":\"SCRTEXT_SUBJ_CODE\"},{\"TypeName\":\"VARCHAR\",\"IsCaseSensitive\":true,\"Name\":\"SCRTEXT_CRSE_NUMB\"},{\"TypeName\":\"VARCHAR\",\"IsCaseSensitive\":true,\"Name\":\"SCRTEXT_EFF_TERM\"},{\"TypeName\":\"VARCHAR\",\"IsCaseSensitive\":true,\"Name\":\"SCRTEXT_TEXT_CODE\"},{\"TypeName\":\"DECIMAL\",\"IsCaseSensitive\":false,\"Name\":\"SCRTEXT_SEQNO\"},{\"TypeName\":\"VARCHAR\",\"IsCaseSensitive\":true,\"Name\":\"SCRTEXT_TEXT\"}]}","",null,"Not open for credit to students who have completed any MGT 271.",1,0,3],["R","20 Day Drop",0,"253",0,4,0,4,null,"Analysis of information systems used for accounting, recordkeeping, and control. Topics include the regulatory requirements of accounting control systems as well as their implementation and auditing considerations.","55062",null,"February, 04 2019 00:00:00","","","","",null,0,"55062","ACC 201;  (MGT 200A or MGP 200A or MGB 200A)","001","ACC","Accounting Systems","Accounting Systems","Winter 19","{\"QUERY\":{\"COLUMNS\":[\"BLDG_DESC\",\"ROOM\",\"BEGIN_TIME\",\"END_TIME\",\"START_DATE\",\"END_DATE\",\"MEET_TYPE_CODE\",\"MEET_TYPE_DESC\",\"MEET_TYPE_DESC_SHORT\",\"SUNDAY\",\"MONDAY\",\"TUESDAY\",\"WEDNESDAY\",\"THURSDAY\",\"FRIDAY\",\"SATURDAY\",\"WEEKDAYS\",\"MEET_CATEGORY\"],\"DATA\":[[\"Gallagher Hall\",\"1213\",null,null,\"January, 07 2019 00:00:00\",\"March, 15 2019 00:00:00\",\"A\",\"Lecture\",\"LEC\",null,null,null,null,null,\"F\",\"S\",\"F,S\",\"01\"]]},\"QUERY_METADATA\":[{\"TypeName\":\"VARCHAR\",\"IsCaseSensitive\":true,\"Name\":\"bldg_desc\"},{\"TypeName\":\"VARCHAR\",\"IsCaseSensitive\":true,\"Name\":\"ROOM\"},{\"TypeName\":\"VARCHAR\",\"IsCaseSensitive\":true,\"Name\":\"begin_time\"},{\"TypeName\":\"VARCHAR\",\"IsCaseSensitive\":true,\"Name\":\"end_time\"},{\"TypeName\":\"TIMESTAMP\",\"IsCaseSensitive\":false,\"Name\":\"start_date\"},{\"TypeName\":\"TIMESTAMP\",\"IsCaseSensitive\":false,\"Name\":\"end_date\"},{\"TypeName\":\"VARCHAR\",\"IsCaseSensitive\":true,\"Name\":\"meet_type_code\"},{\"TypeName\":\"VARCHAR\",\"IsCaseSensitive\":true,\"Name\":\"meet_type_desc\"},{\"TypeName\":\"VARCHAR\",\"IsCaseSensitive\":true,\"Name\":\"meet_type_desc_short\"},{\"TypeName\":\"VARCHAR\",\"IsCaseSensitive\":true,\"Name\":\"sunday\"},{\"TypeName\":\"VARCHAR\",\"IsCaseSensitive\":true,\"Name\":\"monday\"},{\"TypeName\":\"VARCHAR\",\"IsCaseSensitive\":true,\"Name\":\"tuesday\"},{\"TypeName\":\"VARCHAR\",\"IsCaseSensitive\":true,\"Name\":\"wednesday\"},{\"TypeName\":\"VARCHAR\",\"IsCaseSensitive\":true,\"Name\":\"thursday\"},{\"TypeName\":\"VARCHAR\",\"IsCaseSensitive\":true,\"Name\":\"friday\"},{\"TypeName\":\"VARCHAR\",\"IsCaseSensitive\":true,\"Name\":\"saturday\"},{\"TypeName\":\"VARCHAR\",\"IsCaseSensitive\":false,\"Name\":\"WEEKDAYS\"},{\"TypeName\":\"VARCHAR\",\"IsCaseSensitive\":true,\"Name\":\"meet_category\"}]}","{\"QUERY\":{\"COLUMNS\":[\"EMAIL\",\"FIRST_NAME\",\"LAST_NAME\",\"MIDDLE_NAME\",\"CATEGORY\",\"PRIMARY_IND\"],\"DATA\":[[\"cjchang@ucdavis.edu\",\"Chengyee\",\"Chang\",\"J\",\"01\",\"Y\"]]},\"QUERY_METADATA\":[{\"TypeName\":\"VARCHAR\",\"IsCaseSensitive\":true,\"Name\":\"email\"},{\"TypeName\":\"VARCHAR\",\"IsCaseSensitive\":true,\"Name\":\"first_name\"},{\"TypeName\":\"VARCHAR\",\"IsCaseSensitive\":true,\"Name\":\"last_name\"},{\"TypeName\":\"VARCHAR\",\"IsCaseSensitive\":true,\"Name\":\"middle_name\"},{\"TypeName\":\"VARCHAR\",\"IsCaseSensitive\":true,\"Name\":\"category\"},{\"TypeName\":\"VARCHAR\",\"IsCaseSensitive\":true,\"Name\":\"primary_ind\"}]}","","{\"QUERY\":{\"COLUMNS\":[\"SCRTEXT_SUBJ_CODE\",\"SCRTEXT_CRSE_NUMB\",\"SCRTEXT_EFF_TERM\",\"SCRTEXT_TEXT_CODE\",\"SCRTEXT_SEQNO\",\"SCRTEXT_TEXT\"],\"DATA\":[[\"ACC\",\"253\",\"201803\",\"A\",1.00000000000000000000,\"** OPEN TO STUDENTS ENROLLED IN THE MPAC PROGRAM (GPAC) **\"]]},\"QUERY_METADATA\":[{\"TypeName\":\"VARCHAR\",\"IsCaseSensitive\":true,\"Name\":\"SCRTEXT_SUBJ_CODE\"},{\"TypeName\":\"VARCHAR\",\"IsCaseSensitive\":true,\"Name\":\"SCRTEXT_CRSE_NUMB\"},{\"TypeName\":\"VARCHAR\",\"IsCaseSensitive\":true,\"Name\":\"SCRTEXT_EFF_TERM\"},{\"TypeName\":\"VARCHAR\",\"IsCaseSensitive\":true,\"Name\":\"SCRTEXT_TEXT_CODE\"},{\"TypeName\":\"DECIMAL\",\"IsCaseSensitive\":false,\"Name\":\"SCRTEXT_SEQNO\"},{\"TypeName\":\"VARCHAR\",\"IsCaseSensitive\":true,\"Name\":\"SCRTEXT_TEXT\"}]}","",null,"Not open for credit to students who have taken any MGT 271.",2,0,4],["R","20 Day Drop",0,"261",0,4,0,4,null,"Overview of written and oral professional communications with an emphasis on structuring and documenting audits and reports, understanding audiences (investors, creditors, regulators, and other stakeholders), and consideration of ethical and regulatory responsibilities.","20829",null,"February, 04 2019 00:00:00","","","","",null,0,"20829","ACC 201;  (MGT 200A or MGB 200A or MGP 200A)","001","ACC","Accounting Communication","Accounting Communication","Winter 19","{\"QUERY\":{\"COLUMNS\":[\"BLDG_DESC\",\"ROOM\",\"BEGIN_TIME\",\"END_TIME\",\"START_DATE\",\"END_DATE\",\"MEET_TYPE_CODE\",\"MEET_TYPE_DESC\",\"MEET_TYPE_DESC_SHORT\",\"SUNDAY\",\"MONDAY\",\"TUESDAY\",\"WEDNESDAY\",\"THURSDAY\",\"FRIDAY\",\"SATURDAY\",\"WEEKDAYS\",\"MEET_CATEGORY\"],\"DATA\":[[\"Gallagher Hall\",\"2310\",\"0900\",\"1250\",\"January, 07 2019 00:00:00\",\"March, 15 2019 00:00:00\",\"A\",\"Lecture\",\"LEC\",null,null,null,\"W\",null,null,null,\"W\",\"01\"]]},\"QUERY_METADATA\":[{\"TypeName\":\"VARCHAR\",\"IsCaseSensitive\":true,\"Name\":\"bldg_desc\"},{\"TypeName\":\"VARCHAR\",\"IsCaseSensitive\":true,\"Name\":\"ROOM\"},{\"TypeName\":\"VARCHAR\",\"IsCaseSensitive\":true,\"Name\":\"begin_time\"},{\"TypeName\":\"VARCHAR\",\"IsCaseSensitive\":true,\"Name\":\"end_time\"},{\"TypeName\":\"TIMESTAMP\",\"IsCaseSensitive\":false,\"Name\":\"start_date\"},{\"TypeName\":\"TIMESTAMP\",\"IsCaseSensitive\":false,\"Name\":\"end_date\"},{\"TypeName\":\"VARCHAR\",\"IsCaseSensitive\":true,\"Name\":\"meet_type_code\"},{\"TypeName\":\"VARCHAR\",\"IsCaseSensitive\":true,\"Name\":\"meet_type_desc\"},{\"TypeName\":\"VARCHAR\",\"IsCaseSensitive\":true,\"Name\":\"meet_type_desc_short\"},{\"TypeName\":\"VARCHAR\",\"IsCaseSensitive\":true,\"Name\":\"sunday\"},{\"TypeName\":\"VARCHAR\",\"IsCaseSensitive\":true,\"Name\":\"monday\"},{\"TypeName\":\"VARCHAR\",\"IsCaseSensitive\":true,\"Name\":\"tuesday\"},{\"TypeName\":\"VARCHAR\",\"IsCaseSensitive\":true,\"Name\":\"wednesday\"},{\"TypeName\":\"VARCHAR\",\"IsCaseSensitive\":true,\"Name\":\"thursday\"},{\"TypeName\":\"VARCHAR\",\"IsCaseSensitive\":true,\"Name\":\"friday\"},{\"TypeName\":\"VARCHAR\",\"IsCaseSensitive\":true,\"Name\":\"saturday\"},{\"TypeName\":\"VARCHAR\",\"IsCaseSensitive\":false,\"Name\":\"WEEKDAYS\"},{\"TypeName\":\"VARCHAR\",\"IsCaseSensitive\":true,\"Name\":\"meet_category\"}]}","{\"QUERY\":{\"COLUMNS\":[\"EMAIL\",\"FIRST_NAME\",\"LAST_NAME\",\"MIDDLE_NAME\",\"CATEGORY\",\"PRIMARY_IND\"],\"DATA\":[[\"dnykennedy@ucdavis.edu\",\"Joseph\",\"Kennedy\",\"Daniel\",\"01\",\"Y\"]]},\"QUERY_METADATA\":[{\"TypeName\":\"VARCHAR\",\"IsCaseSensitive\":true,\"Name\":\"email\"},{\"TypeName\":\"VARCHAR\",\"IsCaseSensitive\":true,\"Name\":\"first_name\"},{\"TypeName\":\"VARCHAR\",\"IsCaseSensitive\":true,\"Name\":\"last_name\"},{\"TypeName\":\"VARCHAR\",\"IsCaseSensitive\":true,\"Name\":\"middle_name\"},{\"TypeName\":\"VARCHAR\",\"IsCaseSensitive\":true,\"Name\":\"category\"},{\"TypeName\":\"VARCHAR\",\"IsCaseSensitive\":true,\"Name\":\"primary_ind\"}]}","","{\"QUERY\":{\"COLUMNS\":[\"SCRTEXT_SUBJ_CODE\",\"SCRTEXT_CRSE_NUMB\",\"SCRTEXT_EFF_TERM\",\"SCRTEXT_TEXT_CODE\",\"SCRTEXT_SEQNO\",\"SCRTEXT_TEXT\"],\"DATA\":[[\"ACC\",\"261\",\"201801\",\"A\",1.00000000000000000000,\"** OPEN TO STUDENTS ENROLLED IN THE MPAC PROGRAM (GPAC) **\"]]},\"QUERY_METADATA\":[{\"TypeName\":\"VARCHAR\",\"IsCaseSensitive\":true,\"Name\":\"SCRTEXT_SUBJ_CODE\"},{\"TypeName\":\"VARCHAR\",\"IsCaseSensitive\":true,\"Name\":\"SCRTEXT_CRSE_NUMB\"},{\"TypeName\":\"VARCHAR\",\"IsCaseSensitive\":true,\"Name\":\"SCRTEXT_EFF_TERM\"},{\"TypeName\":\"VARCHAR\",\"IsCaseSensitive\":true,\"Name\":\"SCRTEXT_TEXT_CODE\"},{\"TypeName\":\"DECIMAL\",\"IsCaseSensitive\":false,\"Name\":\"SCRTEXT_SEQNO\"},{\"TypeName\":\"VARCHAR\",\"IsCaseSensitive\":true,\"Name\":\"SCRTEXT_TEXT\"}]}","",null,"Not open for credit to students who have taken any MGT 268.",-1,0,5],["R","20 Day Drop",0,"261",0,4,0,4,null,"Overview of written and oral professional communications with an emphasis on structuring and documenting audits and reports, understanding audiences (investors, creditors, regulators, and other stakeholders), and consideration of ethical and regulatory responsibilities.","20830",null,"February, 04 2019 00:00:00","","","","",null,0,"20830","ACC 201;  (MGT 200A or MGB 200A or MGP 200A)","002","ACC","Accounting Communication","Accounting Communication","Winter 19","{\"QUERY\":{\"COLUMNS\":[\"BLDG_DESC\",\"ROOM\",\"BEGIN_TIME\",\"END_TIME\",\"START_DATE\",\"END_DATE\",\"MEET_TYPE_CODE\",\"MEET_TYPE_DESC\",\"MEET_TYPE_DESC_SHORT\",\"SUNDAY\",\"MONDAY\",\"TUESDAY\",\"WEDNESDAY\",\"THURSDAY\",\"FRIDAY\",\"SATURDAY\",\"WEEKDAYS\",\"MEET_CATEGORY\"],\"DATA\":[[\"Gallagher Hall\",\"2310\",\"1310\",\"1700\",\"January, 07 2019 00:00:00\",\"March, 15 2019 00:00:00\",\"A\",\"Lecture\",\"LEC\",null,null,null,\"W\",null,null,null,\"W\",\"01\"]]},\"QUERY_METADATA\":[{\"TypeName\":\"VARCHAR\",\"IsCaseSensitive\":true,\"Name\":\"bldg_desc\"},{\"TypeName\":\"VARCHAR\",\"IsCaseSensitive\":true,\"Name\":\"ROOM\"},{\"TypeName\":\"VARCHAR\",\"IsCaseSensitive\":true,\"Name\":\"begin_time\"},{\"TypeName\":\"VARCHAR\",\"IsCaseSensitive\":true,\"Name\":\"end_time\"},{\"TypeName\":\"TIMESTAMP\",\"IsCaseSensitive\":false,\"Name\":\"start_date\"},{\"TypeName\":\"TIMESTAMP\",\"IsCaseSensitive\":false,\"Name\":\"end_date\"},{\"TypeName\":\"VARCHAR\",\"IsCaseSensitive\":true,\"Name\":\"meet_type_code\"},{\"TypeName\":\"VARCHAR\",\"IsCaseSensitive\":true,\"Name\":\"meet_type_desc\"},{\"TypeName\":\"VARCHAR\",\"IsCaseSensitive\":true,\"Name\":\"meet_type_desc_short\"},{\"TypeName\":\"VARCHAR\",\"IsCaseSensitive\":true,\"Name\":\"sunday\"},{\"TypeName\":\"VARCHAR\",\"IsCaseSensitive\":true,\"Name\":\"monday\"},{\"TypeName\":\"VARCHAR\",\"IsCaseSensitive\":true,\"Name\":\"tuesday\"},{\"TypeName\":\"VARCHAR\",\"IsCaseSensitive\":true,\"Name\":\"wednesday\"},{\"TypeName\":\"VARCHAR\",\"IsCaseSensitive\":true,\"Name\":\"thursday\"},{\"TypeName\":\"VARCHAR\",\"IsCaseSensitive\":true,\"Name\":\"friday\"},{\"TypeName\":\"VARCHAR\",\"IsCaseSensitive\":true,\"Name\":\"saturday\"},{\"TypeName\":\"VARCHAR\",\"IsCaseSensitive\":false,\"Name\":\"WEEKDAYS\"},{\"TypeName\":\"VARCHAR\",\"IsCaseSensitive\":true,\"Name\":\"meet_category\"}]}","{\"QUERY\":{\"COLUMNS\":[\"EMAIL\",\"FIRST_NAME\",\"LAST_NAME\",\"MIDDLE_NAME\",\"CATEGORY\",\"PRIMARY_IND\"],\"DATA\":[[\"bkennedy@ucdavis.edu\",\"Brian\",\"Kennedy\",\"Daniel\",\"01\",\"Y\"]]},\"QUERY_METADATA\":[{\"TypeName\":\"VARCHAR\",\"IsCaseSensitive\":true,\"Name\":\"email\"},{\"TypeName\":\"VARCHAR\",\"IsCaseSensitive\":true,\"Name\":\"first_name\"},{\"TypeName\":\"VARCHAR\",\"IsCaseSensitive\":true,\"Name\":\"last_name\"},{\"TypeName\":\"VARCHAR\",\"IsCaseSensitive\":true,\"Name\":\"middle_name\"},{\"TypeName\":\"VARCHAR\",\"IsCaseSensitive\":true,\"Name\":\"category\"},{\"TypeName\":\"VARCHAR\",\"IsCaseSensitive\":true,\"Name\":\"primary_ind\"}]}","","{\"QUERY\":{\"COLUMNS\":[\"SCRTEXT_SUBJ_CODE\",\"SCRTEXT_CRSE_NUMB\",\"SCRTEXT_EFF_TERM\",\"SCRTEXT_TEXT_CODE\",\"SCRTEXT_SEQNO\",\"SCRTEXT_TEXT\"],\"DATA\":[[\"ACC\",\"261\",\"201801\",\"A\",1.00000000000000000000,\"** OPEN TO STUDENTS ENROLLED IN THE MPAC PROGRAM (GPAC) **\"]]},\"QUERY_METADATA\":[{\"TypeName\":\"VARCHAR\",\"IsCaseSensitive\":true,\"Name\":\"SCRTEXT_SUBJ_CODE\"},{\"TypeName\":\"VARCHAR\",\"IsCaseSensitive\":true,\"Name\":\"SCRTEXT_CRSE_NUMB\"},{\"TypeName\":\"VARCHAR\",\"IsCaseSensitive\":true,\"Name\":\"SCRTEXT_EFF_TERM\"},{\"TypeName\":\"VARCHAR\",\"IsCaseSensitive\":true,\"Name\":\"SCRTEXT_TEXT_CODE\"},{\"TypeName\":\"DECIMAL\",\"IsCaseSensitive\":false,\"Name\":\"SCRTEXT_SEQNO\"},{\"TypeName\":\"VARCHAR\",\"IsCaseSensitive\":true,\"Name\":\"SCRTEXT_TEXT\"}]}","",null,"Not open for credit to students who have taken any MGT 268.",2,0,6]]}} 