{"Success":1,"Results":{"COLUMNS":["ALLOWEDDROPCODE","ALLOWEDDROPDESC","CONSENTOFINSRUCTORREQUIRED","COURSE_NUMBER","CREDIT_HOURS_HIGH","CREDIT_HOURS_LOW","UNITS_HIGH","UNITS_LOW","UNITS_IND","DESCRIPTION","DSPCRN","FINALEXAMSTARTDATE","DROP_DATE","GE2CREDIT","GE3CREDIT","GRADE_MODE_CHOICES","GRADE_MODES_POSSIBLE","GRADE_MODE_CODE","ISVARIABLEUNIT","PASSEDCRN","PREREQUISITES","SEC","SUBJECT_CODE","TITLE","TITLE_SHORT","COURSEMATERIALSTERM","COURSEMEETINGDATA","INSTRUCTORS","COURSEDEPTSPECIFICNOTESDATA","COURSESUBJECTSPECIFICNOTESDATA","COURSESPECIFICNOTESDATA","CROSS_LISTING","CREDIT_LIMITATION","BLEND_SEATS_AVAIL","BLEND_WAIT_COUNT","RECORDNUM"],"DATA":[["E","10 Day Drop",0,"200A",0,3,0,3,null,"Introduction to the concepts and objectives underlying the preparation\nof financial statements. Topics include understanding the accounting cycle, measurement and valuation problems associated with financial statement components, consideration of the usefulness of financial statements in the analysis of a corporation's operations.","43098",null,"January, 18 2019 00:00:00","","","","",null,0,"43098","Graduate student in the Graduate School of Management.","001","MGP","Fin Accounting","Fin Accounting","Winter 19","{\"QUERY\":{\"COLUMNS\":[\"BLDG_DESC\",\"ROOM\",\"BEGIN_TIME\",\"END_TIME\",\"START_DATE\",\"END_DATE\",\"MEET_TYPE_CODE\",\"MEET_TYPE_DESC\",\"MEET_TYPE_DESC_SHORT\",\"SUNDAY\",\"MONDAY\",\"TUESDAY\",\"WEDNESDAY\",\"THURSDAY\",\"FRIDAY\",\"SATURDAY\",\"WEEKDAYS\",\"MEET_CATEGORY\"],\"DATA\":[[\"TBA\",\"TBA\",null,null,\"January, 07 2019 00:00:00\",\"March, 15 2019 00:00:00\",\"A\",\"Lecture\",\"LEC\",null,null,null,null,null,null,\"S\",\"S\",\"01\"]]},\"QUERY_METADATA\":[{\"TypeName\":\"VARCHAR\",\"IsCaseSensitive\":true,\"Name\":\"bldg_desc\"},{\"TypeName\":\"VARCHAR\",\"IsCaseSensitive\":true,\"Name\":\"ROOM\"},{\"TypeName\":\"VARCHAR\",\"IsCaseSensitive\":true,\"Name\":\"begin_time\"},{\"TypeName\":\"VARCHAR\",\"IsCaseSensitive\":true,\"Name\":\"end_time\"},{\"TypeName\":\"TIMESTAMP\",\"IsCaseSensitive\":false,\"Name\":\"start_date\"},{\"TypeName\":\"TIMESTAMP\",\"IsCaseSensitive\":false,\"Name\":\"end_date\"},{\"TypeName\":\"VARCHAR\",\"IsCaseSensitive\":true,\"Name\":\"meet_type_code\"},{\"TypeName\":\"VARCHAR\",\"IsCaseSensitive\":true,\"Name\":\"meet_type_desc\"},{\"TypeName\":\"VARCHAR\",\"IsCaseSensitive\":true,\"Name\":\"meet_type_desc_short\"},{\"TypeName\":\"VARCHAR\",\"IsCaseSensitive\":true,\"Name\":\"sunday\"},{\"TypeName\":\"VARCHAR\",\"IsCaseSensitive\":true,\"Name\":\"monday\"},{\"TypeName\":\"VARCHAR\",\"IsCaseSensitive\":true,\"Name\":\"tuesday\"},{\"TypeName\":\"VARCHAR\",\"IsCaseSensitive\":true,\"Name\":\"wednesday\"},{\"TypeName\":\"VARCHAR\",\"IsCaseSensitive\":true,\"Name\":\"thursday\"},{\"TypeName\":\"VARCHAR\",\"IsCaseSensitive\":true,\"Name\":\"friday\"},{\"TypeName\":\"VARCHAR\",\"IsCaseSensitive\":true,\"Name\":\"saturday\"},{\"TypeName\":\"VARCHAR\",\"IsCaseSensitive\":false,\"Name\":\"WEEKDAYS\"},{\"TypeName\":\"VARCHAR\",\"IsCaseSensitive\":true,\"Name\":\"meet_category\"}]}","{\"QUERY\":{\"COLUMNS\":[\"EMAIL\",\"FIRST_NAME\",\"LAST_NAME\",\"MIDDLE_NAME\",\"CATEGORY\",\"PRIMARY_IND\"],\"DATA\":[[\"haskaife@ucdavis.edu\",\"Hollis\",\"Skaife\",\"A\",\"01\",\"Y\"]]},\"QUERY_METADATA\":[{\"TypeName\":\"VARCHAR\",\"IsCaseSensitive\":true,\"Name\":\"email\"},{\"TypeName\":\"VARCHAR\",\"IsCaseSensitive\":true,\"Name\":\"first_name\"},{\"TypeName\":\"VARCHAR\",\"IsCaseSensitive\":true,\"Name\":\"last_name\"},{\"TypeName\":\"VARCHAR\",\"IsCaseSensitive\":true,\"Name\":\"middle_name\"},{\"TypeName\":\"VARCHAR\",\"IsCaseSensitive\":true,\"Name\":\"category\"},{\"TypeName\":\"VARCHAR\",\"IsCaseSensitive\":true,\"Name\":\"primary_ind\"}]}","","{\"QUERY\":{\"COLUMNS\":[\"SCRTEXT_SUBJ_CODE\",\"SCRTEXT_CRSE_NUMB\",\"SCRTEXT_EFF_TERM\",\"SCRTEXT_TEXT_CODE\",\"SCRTEXT_SEQNO\",\"SCRTEXT_TEXT\"],\"DATA\":[[\"MGP\",\"200A\",\"201801\",\"A\",1.00000000000000000000,\"** OPEN TO STUDENTS IN THE MBA PROGRAM (SMBA, SMBE, SMBB) **\"]]},\"QUERY_METADATA\":[{\"TypeName\":\"VARCHAR\",\"IsCaseSensitive\":true,\"Name\":\"SCRTEXT_SUBJ_CODE\"},{\"TypeName\":\"VARCHAR\",\"IsCaseSensitive\":true,\"Name\":\"SCRTEXT_CRSE_NUMB\"},{\"TypeName\":\"VARCHAR\",\"IsCaseSensitive\":true,\"Name\":\"SCRTEXT_EFF_TERM\"},{\"TypeName\":\"VARCHAR\",\"IsCaseSensitive\":true,\"Name\":\"SCRTEXT_TEXT_CODE\"},{\"TypeName\":\"DECIMAL\",\"IsCaseSensitive\":false,\"Name\":\"SCRTEXT_SEQNO\"},{\"TypeName\":\"VARCHAR\",\"IsCaseSensitive\":true,\"Name\":\"SCRTEXT_TEXT\"}]}","",null,null,16,0,1],["E","10 Day Drop",0,"201B",0,3,0,3,null,"Strategic management of organizations, including analysis of industries, firm resources and capabilities and corporate strategy. Strategy formulation, implementation and strategic decision-making. Firm and industry life cycles and change. Analysis of organizational design and structure including differentiation and integration.","43100",null,"January, 18 2019 00:00:00","","","","",null,0,"43100","Completion of first year courses in Graduate School of Management or equivalent.","001","MGP","Org Strategy & Structure","Org Strategy & Structure","Winter 19","{\"QUERY\":{\"COLUMNS\":[\"BLDG_DESC\",\"ROOM\",\"BEGIN_TIME\",\"END_TIME\",\"START_DATE\",\"END_DATE\",\"MEET_TYPE_CODE\",\"MEET_TYPE_DESC\",\"MEET_TYPE_DESC_SHORT\",\"SUNDAY\",\"MONDAY\",\"TUESDAY\",\"WEDNESDAY\",\"THURSDAY\",\"FRIDAY\",\"SATURDAY\",\"WEEKDAYS\",\"MEET_CATEGORY\"],\"DATA\":[[\"TBA\",\"TBA\",null,null,\"January, 07 2019 00:00:00\",\"March, 15 2019 00:00:00\",\"B\",\"Lecture/Discussion\",\"LED\",null,null,null,null,null,\"F\",null,\"F\",\"01\"]]},\"QUERY_METADATA\":[{\"TypeName\":\"VARCHAR\",\"IsCaseSensitive\":true,\"Name\":\"bldg_desc\"},{\"TypeName\":\"VARCHAR\",\"IsCaseSensitive\":true,\"Name\":\"ROOM\"},{\"TypeName\":\"VARCHAR\",\"IsCaseSensitive\":true,\"Name\":\"begin_time\"},{\"TypeName\":\"VARCHAR\",\"IsCaseSensitive\":true,\"Name\":\"end_time\"},{\"TypeName\":\"TIMESTAMP\",\"IsCaseSensitive\":false,\"Name\":\"start_date\"},{\"TypeName\":\"TIMESTAMP\",\"IsCaseSensitive\":false,\"Name\":\"end_date\"},{\"TypeName\":\"VARCHAR\",\"IsCaseSensitive\":true,\"Name\":\"meet_type_code\"},{\"TypeName\":\"VARCHAR\",\"IsCaseSensitive\":true,\"Name\":\"meet_type_desc\"},{\"TypeName\":\"VARCHAR\",\"IsCaseSensitive\":true,\"Name\":\"meet_type_desc_short\"},{\"TypeName\":\"VARCHAR\",\"IsCaseSensitive\":true,\"Name\":\"sunday\"},{\"TypeName\":\"VARCHAR\",\"IsCaseSensitive\":true,\"Name\":\"monday\"},{\"TypeName\":\"VARCHAR\",\"IsCaseSensitive\":true,\"Name\":\"tuesday\"},{\"TypeName\":\"VARCHAR\",\"IsCaseSensitive\":true,\"Name\":\"wednesday\"},{\"TypeName\":\"VARCHAR\",\"IsCaseSensitive\":true,\"Name\":\"thursday\"},{\"TypeName\":\"VARCHAR\",\"IsCaseSensitive\":true,\"Name\":\"friday\"},{\"TypeName\":\"VARCHAR\",\"IsCaseSensitive\":true,\"Name\":\"saturday\"},{\"TypeName\":\"VARCHAR\",\"IsCaseSensitive\":false,\"Name\":\"WEEKDAYS\"},{\"TypeName\":\"VARCHAR\",\"IsCaseSensitive\":true,\"Name\":\"meet_category\"}]}","{\"QUERY\":{\"COLUMNS\":[\"EMAIL\",\"FIRST_NAME\",\"LAST_NAME\",\"MIDDLE_NAME\",\"CATEGORY\",\"PRIMARY_IND\"],\"DATA\":[[\"gdokko@ucdavis.edu\",\"Gina\",\"Dokko\",null,\"01\",\"Y\"]]},\"QUERY_METADATA\":[{\"TypeName\":\"VARCHAR\",\"IsCaseSensitive\":true,\"Name\":\"email\"},{\"TypeName\":\"VARCHAR\",\"IsCaseSensitive\":true,\"Name\":\"first_name\"},{\"TypeName\":\"VARCHAR\",\"IsCaseSensitive\":true,\"Name\":\"last_name\"},{\"TypeName\":\"VARCHAR\",\"IsCaseSensitive\":true,\"Name\":\"middle_name\"},{\"TypeName\":\"VARCHAR\",\"IsCaseSensitive\":true,\"Name\":\"category\"},{\"TypeName\":\"VARCHAR\",\"IsCaseSensitive\":true,\"Name\":\"primary_ind\"}]}","","{\"QUERY\":{\"COLUMNS\":[\"SCRTEXT_SUBJ_CODE\",\"SCRTEXT_CRSE_NUMB\",\"SCRTEXT_EFF_TERM\",\"SCRTEXT_TEXT_CODE\",\"SCRTEXT_SEQNO\",\"SCRTEXT_TEXT\"],\"DATA\":[[\"MGP\",\"201B\",\"201801\",\"A\",1.00000000000000000000,\"** OPEN TO STUDENTS IN THE MBA PROGRAM (SMBA, SMBE, SMBB) **\"]]},\"QUERY_METADATA\":[{\"TypeName\":\"VARCHAR\",\"IsCaseSensitive\":true,\"Name\":\"SCRTEXT_SUBJ_CODE\"},{\"TypeName\":\"VARCHAR\",\"IsCaseSensitive\":true,\"Name\":\"SCRTEXT_CRSE_NUMB\"},{\"TypeName\":\"VARCHAR\",\"IsCaseSensitive\":true,\"Name\":\"SCRTEXT_EFF_TERM\"},{\"TypeName\":\"VARCHAR\",\"IsCaseSensitive\":true,\"Name\":\"SCRTEXT_TEXT_CODE\"},{\"TypeName\":\"DECIMAL\",\"IsCaseSensitive\":false,\"Name\":\"SCRTEXT_SEQNO\"},{\"TypeName\":\"VARCHAR\",\"IsCaseSensitive\":true,\"Name\":\"SCRTEXT_TEXT\"}]}","",null,null,25,0,2],["E","10 Day Drop",0,"201B",0,3,0,3,null,"Strategic management of organizations, including analysis of industries, firm resources and capabilities and corporate strategy. Strategy formulation, implementation and strategic decision-making. Firm and industry life cycles and change. Analysis of organizational design and structure including differentiation and integration.","55220",null,"January, 18 2019 00:00:00","","","","",null,0,"55220","Completion of first year courses in Graduate School of Management or equivalent.","002","MGP","Org Strategy & Structure","Org Strategy & Structure","Winter 19","{\"QUERY\":{\"COLUMNS\":[\"BLDG_DESC\",\"ROOM\",\"BEGIN_TIME\",\"END_TIME\",\"START_DATE\",\"END_DATE\",\"MEET_TYPE_CODE\",\"MEET_TYPE_DESC\",\"MEET_TYPE_DESC_SHORT\",\"SUNDAY\",\"MONDAY\",\"TUESDAY\",\"WEDNESDAY\",\"THURSDAY\",\"FRIDAY\",\"SATURDAY\",\"WEEKDAYS\",\"MEET_CATEGORY\"],\"DATA\":[[\"Off Campus\",null,\"1730\",\"2030\",\"January, 07 2019 00:00:00\",\"March, 15 2019 00:00:00\",\"B\",\"Lecture/Discussion\",\"LED\",null,null,\"T\",null,null,null,null,\"T\",\"01\"]]},\"QUERY_METADATA\":[{\"TypeName\":\"VARCHAR\",\"IsCaseSensitive\":true,\"Name\":\"bldg_desc\"},{\"TypeName\":\"VARCHAR\",\"IsCaseSensitive\":true,\"Name\":\"ROOM\"},{\"TypeName\":\"VARCHAR\",\"IsCaseSensitive\":true,\"Name\":\"begin_time\"},{\"TypeName\":\"VARCHAR\",\"IsCaseSensitive\":true,\"Name\":\"end_time\"},{\"TypeName\":\"TIMESTAMP\",\"IsCaseSensitive\":false,\"Name\":\"start_date\"},{\"TypeName\":\"TIMESTAMP\",\"IsCaseSensitive\":false,\"Name\":\"end_date\"},{\"TypeName\":\"VARCHAR\",\"IsCaseSensitive\":true,\"Name\":\"meet_type_code\"},{\"TypeName\":\"VARCHAR\",\"IsCaseSensitive\":true,\"Name\":\"meet_type_desc\"},{\"TypeName\":\"VARCHAR\",\"IsCaseSensitive\":true,\"Name\":\"meet_type_desc_short\"},{\"TypeName\":\"VARCHAR\",\"IsCaseSensitive\":true,\"Name\":\"sunday\"},{\"TypeName\":\"VARCHAR\",\"IsCaseSensitive\":true,\"Name\":\"monday\"},{\"TypeName\":\"VARCHAR\",\"IsCaseSensitive\":true,\"Name\":\"tuesday\"},{\"TypeName\":\"VARCHAR\",\"IsCaseSensitive\":true,\"Name\":\"wednesday\"},{\"TypeName\":\"VARCHAR\",\"IsCaseSensitive\":true,\"Name\":\"thursday\"},{\"TypeName\":\"VARCHAR\",\"IsCaseSensitive\":true,\"Name\":\"friday\"},{\"TypeName\":\"VARCHAR\",\"IsCaseSensitive\":true,\"Name\":\"saturday\"},{\"TypeName\":\"VARCHAR\",\"IsCaseSensitive\":false,\"Name\":\"WEEKDAYS\"},{\"TypeName\":\"VARCHAR\",\"IsCaseSensitive\":true,\"Name\":\"meet_category\"}]}","{\"QUERY\":{\"COLUMNS\":[\"EMAIL\",\"FIRST_NAME\",\"LAST_NAME\",\"MIDDLE_NAME\",\"CATEGORY\",\"PRIMARY_IND\"],\"DATA\":[[\"basaraniti@ucdavis.edu\",\"Brett\",\"Saraniti\",\"A\",\"01\",\"Y\"]]},\"QUERY_METADATA\":[{\"TypeName\":\"VARCHAR\",\"IsCaseSensitive\":true,\"Name\":\"email\"},{\"TypeName\":\"VARCHAR\",\"IsCaseSensitive\":true,\"Name\":\"first_name\"},{\"TypeName\":\"VARCHAR\",\"IsCaseSensitive\":true,\"Name\":\"last_name\"},{\"TypeName\":\"VARCHAR\",\"IsCaseSensitive\":true,\"Name\":\"middle_name\"},{\"TypeName\":\"VARCHAR\",\"IsCaseSensitive\":true,\"Name\":\"category\"},{\"TypeName\":\"VARCHAR\",\"IsCaseSensitive\":true,\"Name\":\"primary_ind\"}]}","","{\"QUERY\":{\"COLUMNS\":[\"SCRTEXT_SUBJ_CODE\",\"SCRTEXT_CRSE_NUMB\",\"SCRTEXT_EFF_TERM\",\"SCRTEXT_TEXT_CODE\",\"SCRTEXT_SEQNO\",\"SCRTEXT_TEXT\"],\"DATA\":[[\"MGP\",\"201B\",\"201801\",\"A\",1.00000000000000000000,\"** OPEN TO STUDENTS IN THE MBA PROGRAM (SMBA, SMBE, SMBB) **\"]]},\"QUERY_METADATA\":[{\"TypeName\":\"VARCHAR\",\"IsCaseSensitive\":true,\"Name\":\"SCRTEXT_SUBJ_CODE\"},{\"TypeName\":\"VARCHAR\",\"IsCaseSensitive\":true,\"Name\":\"SCRTEXT_CRSE_NUMB\"},{\"TypeName\":\"VARCHAR\",\"IsCaseSensitive\":true,\"Name\":\"SCRTEXT_EFF_TERM\"},{\"TypeName\":\"VARCHAR\",\"IsCaseSensitive\":true,\"Name\":\"SCRTEXT_TEXT_CODE\"},{\"TypeName\":\"DECIMAL\",\"IsCaseSensitive\":false,\"Name\":\"SCRTEXT_SEQNO\"},{\"TypeName\":\"VARCHAR\",\"IsCaseSensitive\":true,\"Name\":\"SCRTEXT_TEXT\"}]}","",null,null,3,0,3],["E","10 Day Drop",0,"203B",0,3,0,3,null,"Practical statistical methods for managerial decision making covers regression analysis, time series analysis and forecasting, design and analysis of experiments in managerial research and contingency table analysis. Application of these methods to marketing, finance, accounting, production, operations, and public policy.","43101",null,"January, 18 2019 00:00:00","","","","",null,0,"43101","MGP 203A or MGT 203A or MGB 203A","001","MGP","Fore Man Res Meth","Fore Man Res Meth","Winter 19","{\"QUERY\":{\"COLUMNS\":[\"BLDG_DESC\",\"ROOM\",\"BEGIN_TIME\",\"END_TIME\",\"START_DATE\",\"END_DATE\",\"MEET_TYPE_CODE\",\"MEET_TYPE_DESC\",\"MEET_TYPE_DESC_SHORT\",\"SUNDAY\",\"MONDAY\",\"TUESDAY\",\"WEDNESDAY\",\"THURSDAY\",\"FRIDAY\",\"SATURDAY\",\"WEEKDAYS\",\"MEET_CATEGORY\"],\"DATA\":[[\"Sac. Med. Center\",null,\"1800\",\"2100\",\"January, 07 2019 00:00:00\",\"March, 15 2019 00:00:00\",\"A\",\"Lecture\",\"LEC\",null,null,null,null,\"R\",null,null,\"R\",\"01\"]]},\"QUERY_METADATA\":[{\"TypeName\":\"VARCHAR\",\"IsCaseSensitive\":true,\"Name\":\"bldg_desc\"},{\"TypeName\":\"VARCHAR\",\"IsCaseSensitive\":true,\"Name\":\"ROOM\"},{\"TypeName\":\"VARCHAR\",\"IsCaseSensitive\":true,\"Name\":\"begin_time\"},{\"TypeName\":\"VARCHAR\",\"IsCaseSensitive\":true,\"Name\":\"end_time\"},{\"TypeName\":\"TIMESTAMP\",\"IsCaseSensitive\":false,\"Name\":\"start_date\"},{\"TypeName\":\"TIMESTAMP\",\"IsCaseSensitive\":false,\"Name\":\"end_date\"},{\"TypeName\":\"VARCHAR\",\"IsCaseSensitive\":true,\"Name\":\"meet_type_code\"},{\"TypeName\":\"VARCHAR\",\"IsCaseSensitive\":true,\"Name\":\"meet_type_desc\"},{\"TypeName\":\"VARCHAR\",\"IsCaseSensitive\":true,\"Name\":\"meet_type_desc_short\"},{\"TypeName\":\"VARCHAR\",\"IsCaseSensitive\":true,\"Name\":\"sunday\"},{\"TypeName\":\"VARCHAR\",\"IsCaseSensitive\":true,\"Name\":\"monday\"},{\"TypeName\":\"VARCHAR\",\"IsCaseSensitive\":true,\"Name\":\"tuesday\"},{\"TypeName\":\"VARCHAR\",\"IsCaseSensitive\":true,\"Name\":\"wednesday\"},{\"TypeName\":\"VARCHAR\",\"IsCaseSensitive\":true,\"Name\":\"thursday\"},{\"TypeName\":\"VARCHAR\",\"IsCaseSensitive\":true,\"Name\":\"friday\"},{\"TypeName\":\"VARCHAR\",\"IsCaseSensitive\":true,\"Name\":\"saturday\"},{\"TypeName\":\"VARCHAR\",\"IsCaseSensitive\":false,\"Name\":\"WEEKDAYS\"},{\"TypeName\":\"VARCHAR\",\"IsCaseSensitive\":true,\"Name\":\"meet_category\"}]}","{\"QUERY\":{\"COLUMNS\":[\"EMAIL\",\"FIRST_NAME\",\"LAST_NAME\",\"MIDDLE_NAME\",\"CATEGORY\",\"PRIMARY_IND\"],\"DATA\":[[\"cltsai@ucdavis.edu\",\"Chih-Ling\",\"Tsai\",null,\"01\",\"Y\"]]},\"QUERY_METADATA\":[{\"TypeName\":\"VARCHAR\",\"IsCaseSensitive\":true,\"Name\":\"email\"},{\"TypeName\":\"VARCHAR\",\"IsCaseSensitive\":true,\"Name\":\"first_name\"},{\"TypeName\":\"VARCHAR\",\"IsCaseSensitive\":true,\"Name\":\"last_name\"},{\"TypeName\":\"VARCHAR\",\"IsCaseSensitive\":true,\"Name\":\"middle_name\"},{\"TypeName\":\"VARCHAR\",\"IsCaseSensitive\":true,\"Name\":\"category\"},{\"TypeName\":\"VARCHAR\",\"IsCaseSensitive\":true,\"Name\":\"primary_ind\"}]}","","{\"QUERY\":{\"COLUMNS\":[\"SCRTEXT_SUBJ_CODE\",\"SCRTEXT_CRSE_NUMB\",\"SCRTEXT_EFF_TERM\",\"SCRTEXT_TEXT_CODE\",\"SCRTEXT_SEQNO\",\"SCRTEXT_TEXT\"],\"DATA\":[[\"MGP\",\"203B\",\"201801\",\"A\",1.00000000000000000000,\"** OPEN TO STUDENTS IN THE MBA PROGRAM (SMBA, SMBE, SMBB) **\"]]},\"QUERY_METADATA\":[{\"TypeName\":\"VARCHAR\",\"IsCaseSensitive\":true,\"Name\":\"SCRTEXT_SUBJ_CODE\"},{\"TypeName\":\"VARCHAR\",\"IsCaseSensitive\":true,\"Name\":\"SCRTEXT_CRSE_NUMB\"},{\"TypeName\":\"VARCHAR\",\"IsCaseSensitive\":true,\"Name\":\"SCRTEXT_EFF_TERM\"},{\"TypeName\":\"VARCHAR\",\"IsCaseSensitive\":true,\"Name\":\"SCRTEXT_TEXT_CODE\"},{\"TypeName\":\"DECIMAL\",\"IsCaseSensitive\":false,\"Name\":\"SCRTEXT_SEQNO\"},{\"TypeName\":\"VARCHAR\",\"IsCaseSensitive\":true,\"Name\":\"SCRTEXT_TEXT\"}]}","",null,null,17,0,4],["E","10 Day Drop",0,"204",0,3,0,3,null,"Analysis of market opportunities, elements of market research, development of marketing strategies, market planning and implementations, and control systems. Consumer and industrial markets, market segmentation, pricing strategies, distribution channels, promotion, and sales.","43102",null,"January, 18 2019 00:00:00","","","","",null,0,"43102","Graduate student in the Graduate School of Management.","001","MGP","Marketing Mngmt","Marketing Mngmt","Winter 19","{\"QUERY\":{\"COLUMNS\":[\"BLDG_DESC\",\"ROOM\",\"BEGIN_TIME\",\"END_TIME\",\"START_DATE\",\"END_DATE\",\"MEET_TYPE_CODE\",\"MEET_TYPE_DESC\",\"MEET_TYPE_DESC_SHORT\",\"SUNDAY\",\"MONDAY\",\"TUESDAY\",\"WEDNESDAY\",\"THURSDAY\",\"FRIDAY\",\"SATURDAY\",\"WEEKDAYS\",\"MEET_CATEGORY\"],\"DATA\":[[\"TBA\",\"TBA\",null,null,\"January, 07 2019 00:00:00\",\"March, 15 2019 00:00:00\",\"A\",\"Lecture\",\"LEC\",null,null,null,null,null,\"F\",null,\"F\",\"01\"]]},\"QUERY_METADATA\":[{\"TypeName\":\"VARCHAR\",\"IsCaseSensitive\":true,\"Name\":\"bldg_desc\"},{\"TypeName\":\"VARCHAR\",\"IsCaseSensitive\":true,\"Name\":\"ROOM\"},{\"TypeName\":\"VARCHAR\",\"IsCaseSensitive\":true,\"Name\":\"begin_time\"},{\"TypeName\":\"VARCHAR\",\"IsCaseSensitive\":true,\"Name\":\"end_time\"},{\"TypeName\":\"TIMESTAMP\",\"IsCaseSensitive\":false,\"Name\":\"start_date\"},{\"TypeName\":\"TIMESTAMP\",\"IsCaseSensitive\":false,\"Name\":\"end_date\"},{\"TypeName\":\"VARCHAR\",\"IsCaseSensitive\":true,\"Name\":\"meet_type_code\"},{\"TypeName\":\"VARCHAR\",\"IsCaseSensitive\":true,\"Name\":\"meet_type_desc\"},{\"TypeName\":\"VARCHAR\",\"IsCaseSensitive\":true,\"Name\":\"meet_type_desc_short\"},{\"TypeName\":\"VARCHAR\",\"IsCaseSensitive\":true,\"Name\":\"sunday\"},{\"TypeName\":\"VARCHAR\",\"IsCaseSensitive\":true,\"Name\":\"monday\"},{\"TypeName\":\"VARCHAR\",\"IsCaseSensitive\":true,\"Name\":\"tuesday\"},{\"TypeName\":\"VARCHAR\",\"IsCaseSensitive\":true,\"Name\":\"wednesday\"},{\"TypeName\":\"VARCHAR\",\"IsCaseSensitive\":true,\"Name\":\"thursday\"},{\"TypeName\":\"VARCHAR\",\"IsCaseSensitive\":true,\"Name\":\"friday\"},{\"TypeName\":\"VARCHAR\",\"IsCaseSensitive\":true,\"Name\":\"saturday\"},{\"TypeName\":\"VARCHAR\",\"IsCaseSensitive\":false,\"Name\":\"WEEKDAYS\"},{\"TypeName\":\"VARCHAR\",\"IsCaseSensitive\":true,\"Name\":\"meet_category\"}]}","{\"QUERY\":{\"COLUMNS\":[\"EMAIL\",\"FIRST_NAME\",\"LAST_NAME\",\"MIDDLE_NAME\",\"CATEGORY\",\"PRIMARY_IND\"],\"DATA\":[[\"sptong@ucdavis.edu\",\"Pingsheng\",\"Tong\",null,\"01\",\"Y\"]]},\"QUERY_METADATA\":[{\"TypeName\":\"VARCHAR\",\"IsCaseSensitive\":true,\"Name\":\"email\"},{\"TypeName\":\"VARCHAR\",\"IsCaseSensitive\":true,\"Name\":\"first_name\"},{\"TypeName\":\"VARCHAR\",\"IsCaseSensitive\":true,\"Name\":\"last_name\"},{\"TypeName\":\"VARCHAR\",\"IsCaseSensitive\":true,\"Name\":\"middle_name\"},{\"TypeName\":\"VARCHAR\",\"IsCaseSensitive\":true,\"Name\":\"category\"},{\"TypeName\":\"VARCHAR\",\"IsCaseSensitive\":true,\"Name\":\"primary_ind\"}]}","","{\"QUERY\":{\"COLUMNS\":[\"SCRTEXT_SUBJ_CODE\",\"SCRTEXT_CRSE_NUMB\",\"SCRTEXT_EFF_TERM\",\"SCRTEXT_TEXT_CODE\",\"SCRTEXT_SEQNO\",\"SCRTEXT_TEXT\"],\"DATA\":[[\"MGP\",\"204\",\"201801\",\"A\",1.00000000000000000000,\"** OPEN TO STUDENTS IN THE MBA PROGRAM (SMBA, SMBE, SMBB) **\"]]},\"QUERY_METADATA\":[{\"TypeName\":\"VARCHAR\",\"IsCaseSensitive\":true,\"Name\":\"SCRTEXT_SUBJ_CODE\"},{\"TypeName\":\"VARCHAR\",\"IsCaseSensitive\":true,\"Name\":\"SCRTEXT_CRSE_NUMB\"},{\"TypeName\":\"VARCHAR\",\"IsCaseSensitive\":true,\"Name\":\"SCRTEXT_EFF_TERM\"},{\"TypeName\":\"VARCHAR\",\"IsCaseSensitive\":true,\"Name\":\"SCRTEXT_TEXT_CODE\"},{\"TypeName\":\"DECIMAL\",\"IsCaseSensitive\":false,\"Name\":\"SCRTEXT_SEQNO\"},{\"TypeName\":\"VARCHAR\",\"IsCaseSensitive\":true,\"Name\":\"SCRTEXT_TEXT\"}]}","",null,null,16,0,5],["R","20 Day Drop",0,"244",0,3,0,3,null,"Student teams develop complete business plans for their own start-up ventures.  Process includes: elevator pitch, business strategy, comprehensive bottoms-up financial projections, capital requirements, product differentiation, competitive, alliance, and go-to-market strategy development, investor presentation, and comprehensive written business plan.","43106",null,"February, 04 2019 00:00:00","","","","",null,0,"43106","MGT 204 or MGB 204 or MGP 204","001","MGP","New & Small Bus Ven","New & Small Bus Ven","Winter 19","{\"QUERY\":{\"COLUMNS\":[\"BLDG_DESC\",\"ROOM\",\"BEGIN_TIME\",\"END_TIME\",\"START_DATE\",\"END_DATE\",\"MEET_TYPE_CODE\",\"MEET_TYPE_DESC\",\"MEET_TYPE_DESC_SHORT\",\"SUNDAY\",\"MONDAY\",\"TUESDAY\",\"WEDNESDAY\",\"THURSDAY\",\"FRIDAY\",\"SATURDAY\",\"WEEKDAYS\",\"MEET_CATEGORY\"],\"DATA\":[[\"Gallagher Hall\",\"2310\",\"1830\",\"2130\",\"January, 07 2019 00:00:00\",\"March, 15 2019 00:00:00\",\"A\",\"Lecture\",\"LEC\",null,null,null,\"W\",null,null,null,\"W\",\"01\"]]},\"QUERY_METADATA\":[{\"TypeName\":\"VARCHAR\",\"IsCaseSensitive\":true,\"Name\":\"bldg_desc\"},{\"TypeName\":\"VARCHAR\",\"IsCaseSensitive\":true,\"Name\":\"ROOM\"},{\"TypeName\":\"VARCHAR\",\"IsCaseSensitive\":true,\"Name\":\"begin_time\"},{\"TypeName\":\"VARCHAR\",\"IsCaseSensitive\":true,\"Name\":\"end_time\"},{\"TypeName\":\"TIMESTAMP\",\"IsCaseSensitive\":false,\"Name\":\"start_date\"},{\"TypeName\":\"TIMESTAMP\",\"IsCaseSensitive\":false,\"Name\":\"end_date\"},{\"TypeName\":\"VARCHAR\",\"IsCaseSensitive\":true,\"Name\":\"meet_type_code\"},{\"TypeName\":\"VARCHAR\",\"IsCaseSensitive\":true,\"Name\":\"meet_type_desc\"},{\"TypeName\":\"VARCHAR\",\"IsCaseSensitive\":true,\"Name\":\"meet_type_desc_short\"},{\"TypeName\":\"VARCHAR\",\"IsCaseSensitive\":true,\"Name\":\"sunday\"},{\"TypeName\":\"VARCHAR\",\"IsCaseSensitive\":true,\"Name\":\"monday\"},{\"TypeName\":\"VARCHAR\",\"IsCaseSensitive\":true,\"Name\":\"tuesday\"},{\"TypeName\":\"VARCHAR\",\"IsCaseSensitive\":true,\"Name\":\"wednesday\"},{\"TypeName\":\"VARCHAR\",\"IsCaseSensitive\":true,\"Name\":\"thursday\"},{\"TypeName\":\"VARCHAR\",\"IsCaseSensitive\":true,\"Name\":\"friday\"},{\"TypeName\":\"VARCHAR\",\"IsCaseSensitive\":true,\"Name\":\"saturday\"},{\"TypeName\":\"VARCHAR\",\"IsCaseSensitive\":false,\"Name\":\"WEEKDAYS\"},{\"TypeName\":\"VARCHAR\",\"IsCaseSensitive\":true,\"Name\":\"meet_category\"}]}","{\"QUERY\":{\"COLUMNS\":[\"EMAIL\",\"FIRST_NAME\",\"LAST_NAME\",\"MIDDLE_NAME\",\"CATEGORY\",\"PRIMARY_IND\"],\"DATA\":[[\"mdlowe@ucdavis.edu\",\"Marcus\",\"Lowe\",\"D\",\"01\",\"Y\"]]},\"QUERY_METADATA\":[{\"TypeName\":\"VARCHAR\",\"IsCaseSensitive\":true,\"Name\":\"email\"},{\"TypeName\":\"VARCHAR\",\"IsCaseSensitive\":true,\"Name\":\"first_name\"},{\"TypeName\":\"VARCHAR\",\"IsCaseSensitive\":true,\"Name\":\"last_name\"},{\"TypeName\":\"VARCHAR\",\"IsCaseSensitive\":true,\"Name\":\"middle_name\"},{\"TypeName\":\"VARCHAR\",\"IsCaseSensitive\":true,\"Name\":\"category\"},{\"TypeName\":\"VARCHAR\",\"IsCaseSensitive\":true,\"Name\":\"primary_ind\"}]}","","{\"QUERY\":{\"COLUMNS\":[\"SCRTEXT_SUBJ_CODE\",\"SCRTEXT_CRSE_NUMB\",\"SCRTEXT_EFF_TERM\",\"SCRTEXT_TEXT_CODE\",\"SCRTEXT_SEQNO\",\"SCRTEXT_TEXT\"],\"DATA\":[[\"MGP\",\"244\",\"201801\",\"A\",1.00000000000000000000,\"** OPEN TO STUDENTS IN THE MBA PROGRAM (SMBA, SMBE, SMBB) **\"]]},\"QUERY_METADATA\":[{\"TypeName\":\"VARCHAR\",\"IsCaseSensitive\":true,\"Name\":\"SCRTEXT_SUBJ_CODE\"},{\"TypeName\":\"VARCHAR\",\"IsCaseSensitive\":true,\"Name\":\"SCRTEXT_CRSE_NUMB\"},{\"TypeName\":\"VARCHAR\",\"IsCaseSensitive\":true,\"Name\":\"SCRTEXT_EFF_TERM\"},{\"TypeName\":\"VARCHAR\",\"IsCaseSensitive\":true,\"Name\":\"SCRTEXT_TEXT_CODE\"},{\"TypeName\":\"DECIMAL\",\"IsCaseSensitive\":false,\"Name\":\"SCRTEXT_SEQNO\"},{\"TypeName\":\"VARCHAR\",\"IsCaseSensitive\":true,\"Name\":\"SCRTEXT_TEXT\"}]}","",null,null,6,0,6],["E","10 Day Drop",0,"246",0,3,0,3,null,"Basic theory of negotiation; applies theory to process of building teams to achieve business purposes. Covers integrative and distributive strategies of claiming value, how to recognize bargaining tricks, uncovering hidden agendas, brainstorming to extend Pareto frontier.","43107",null,"January, 18 2019 00:00:00","","","","",null,0,"43107","MGP 205;  MGP 202.","001","MGP","Negotiations","Negotiations","Winter 19","{\"QUERY\":{\"COLUMNS\":[\"BLDG_DESC\",\"ROOM\",\"BEGIN_TIME\",\"END_TIME\",\"START_DATE\",\"END_DATE\",\"MEET_TYPE_CODE\",\"MEET_TYPE_DESC\",\"MEET_TYPE_DESC_SHORT\",\"SUNDAY\",\"MONDAY\",\"TUESDAY\",\"WEDNESDAY\",\"THURSDAY\",\"FRIDAY\",\"SATURDAY\",\"WEEKDAYS\",\"MEET_CATEGORY\"],\"DATA\":[[\"Sac. Med. Center\",null,\"1810\",\"2100\",\"January, 07 2019 00:00:00\",\"March, 15 2019 00:00:00\",\"B\",\"Lecture/Discussion\",\"LED\",null,null,\"T\",null,null,null,null,\"T\",\"01\"]]},\"QUERY_METADATA\":[{\"TypeName\":\"VARCHAR\",\"IsCaseSensitive\":true,\"Name\":\"bldg_desc\"},{\"TypeName\":\"VARCHAR\",\"IsCaseSensitive\":true,\"Name\":\"ROOM\"},{\"TypeName\":\"VARCHAR\",\"IsCaseSensitive\":true,\"Name\":\"begin_time\"},{\"TypeName\":\"VARCHAR\",\"IsCaseSensitive\":true,\"Name\":\"end_time\"},{\"TypeName\":\"TIMESTAMP\",\"IsCaseSensitive\":false,\"Name\":\"start_date\"},{\"TypeName\":\"TIMESTAMP\",\"IsCaseSensitive\":false,\"Name\":\"end_date\"},{\"TypeName\":\"VARCHAR\",\"IsCaseSensitive\":true,\"Name\":\"meet_type_code\"},{\"TypeName\":\"VARCHAR\",\"IsCaseSensitive\":true,\"Name\":\"meet_type_desc\"},{\"TypeName\":\"VARCHAR\",\"IsCaseSensitive\":true,\"Name\":\"meet_type_desc_short\"},{\"TypeName\":\"VARCHAR\",\"IsCaseSensitive\":true,\"Name\":\"sunday\"},{\"TypeName\":\"VARCHAR\",\"IsCaseSensitive\":true,\"Name\":\"monday\"},{\"TypeName\":\"VARCHAR\",\"IsCaseSensitive\":true,\"Name\":\"tuesday\"},{\"TypeName\":\"VARCHAR\",\"IsCaseSensitive\":true,\"Name\":\"wednesday\"},{\"TypeName\":\"VARCHAR\",\"IsCaseSensitive\":true,\"Name\":\"thursday\"},{\"TypeName\":\"VARCHAR\",\"IsCaseSensitive\":true,\"Name\":\"friday\"},{\"TypeName\":\"VARCHAR\",\"IsCaseSensitive\":true,\"Name\":\"saturday\"},{\"TypeName\":\"VARCHAR\",\"IsCaseSensitive\":false,\"Name\":\"WEEKDAYS\"},{\"TypeName\":\"VARCHAR\",\"IsCaseSensitive\":true,\"Name\":\"meet_category\"}]}","{\"QUERY\":{\"COLUMNS\":[\"EMAIL\",\"FIRST_NAME\",\"LAST_NAME\",\"MIDDLE_NAME\",\"CATEGORY\",\"PRIMARY_IND\"],\"DATA\":[[\"jimolson@ucdavis.edu\",\"James\",\"Olson\",\"D\",\"01\",\"Y\"]]},\"QUERY_METADATA\":[{\"TypeName\":\"VARCHAR\",\"IsCaseSensitive\":true,\"Name\":\"email\"},{\"TypeName\":\"VARCHAR\",\"IsCaseSensitive\":true,\"Name\":\"first_name\"},{\"TypeName\":\"VARCHAR\",\"IsCaseSensitive\":true,\"Name\":\"last_name\"},{\"TypeName\":\"VARCHAR\",\"IsCaseSensitive\":true,\"Name\":\"middle_name\"},{\"TypeName\":\"VARCHAR\",\"IsCaseSensitive\":true,\"Name\":\"category\"},{\"TypeName\":\"VARCHAR\",\"IsCaseSensitive\":true,\"Name\":\"primary_ind\"}]}","","{\"QUERY\":{\"COLUMNS\":[\"SCRTEXT_SUBJ_CODE\",\"SCRTEXT_CRSE_NUMB\",\"SCRTEXT_EFF_TERM\",\"SCRTEXT_TEXT_CODE\",\"SCRTEXT_SEQNO\",\"SCRTEXT_TEXT\"],\"DATA\":[[\"MGP\",\"246\",\"201801\",\"A\",1.00000000000000000000,\"** OPEN TO STUDENTS IN THE MBA PROGRAM (SMBA, SMBE, SMBB) **\"]]},\"QUERY_METADATA\":[{\"TypeName\":\"VARCHAR\",\"IsCaseSensitive\":true,\"Name\":\"SCRTEXT_SUBJ_CODE\"},{\"TypeName\":\"VARCHAR\",\"IsCaseSensitive\":true,\"Name\":\"SCRTEXT_CRSE_NUMB\"},{\"TypeName\":\"VARCHAR\",\"IsCaseSensitive\":true,\"Name\":\"SCRTEXT_EFF_TERM\"},{\"TypeName\":\"VARCHAR\",\"IsCaseSensitive\":true,\"Name\":\"SCRTEXT_TEXT_CODE\"},{\"TypeName\":\"DECIMAL\",\"IsCaseSensitive\":false,\"Name\":\"SCRTEXT_SEQNO\"},{\"TypeName\":\"VARCHAR\",\"IsCaseSensitive\":true,\"Name\":\"SCRTEXT_TEXT\"}]}","",null,null,19,0,7],["E","10 Day Drop",0,"249",0,3,0,3,null,"Course addresses the managerial issues and problems of systematically gathering and analyzing information for making private and public marketing decisions. Covers the cost and value of information, research design, information collection, measuring instruments, data analysis, and marketing research applications.","55611",null,"January, 18 2019 00:00:00","","","","",null,0,"55611","(MGT 202A or MGB 202A or MGP 202A);  (MGP 203A or MGB 203A or MGT 203A);  (MGT 204 or MGB 204 or MGP 204)","001","MGP","Marketing Research","Marketing Research","Winter 19","{\"QUERY\":{\"COLUMNS\":[\"BLDG_DESC\",\"ROOM\",\"BEGIN_TIME\",\"END_TIME\",\"START_DATE\",\"END_DATE\",\"MEET_TYPE_CODE\",\"MEET_TYPE_DESC\",\"MEET_TYPE_DESC_SHORT\",\"SUNDAY\",\"MONDAY\",\"TUESDAY\",\"WEDNESDAY\",\"THURSDAY\",\"FRIDAY\",\"SATURDAY\",\"WEEKDAYS\",\"MEET_CATEGORY\"],\"DATA\":[[\"Sac. Med. Center\",null,null,null,\"January, 07 2019 00:00:00\",\"March, 15 2019 00:00:00\",\"A\",\"Lecture\",\"LEC\",null,null,null,null,null,null,\"S\",\"S\",\"01\"]]},\"QUERY_METADATA\":[{\"TypeName\":\"VARCHAR\",\"IsCaseSensitive\":true,\"Name\":\"bldg_desc\"},{\"TypeName\":\"VARCHAR\",\"IsCaseSensitive\":true,\"Name\":\"ROOM\"},{\"TypeName\":\"VARCHAR\",\"IsCaseSensitive\":true,\"Name\":\"begin_time\"},{\"TypeName\":\"VARCHAR\",\"IsCaseSensitive\":true,\"Name\":\"end_time\"},{\"TypeName\":\"TIMESTAMP\",\"IsCaseSensitive\":false,\"Name\":\"start_date\"},{\"TypeName\":\"TIMESTAMP\",\"IsCaseSensitive\":false,\"Name\":\"end_date\"},{\"TypeName\":\"VARCHAR\",\"IsCaseSensitive\":true,\"Name\":\"meet_type_code\"},{\"TypeName\":\"VARCHAR\",\"IsCaseSensitive\":true,\"Name\":\"meet_type_desc\"},{\"TypeName\":\"VARCHAR\",\"IsCaseSensitive\":true,\"Name\":\"meet_type_desc_short\"},{\"TypeName\":\"VARCHAR\",\"IsCaseSensitive\":true,\"Name\":\"sunday\"},{\"TypeName\":\"VARCHAR\",\"IsCaseSensitive\":true,\"Name\":\"monday\"},{\"TypeName\":\"VARCHAR\",\"IsCaseSensitive\":true,\"Name\":\"tuesday\"},{\"TypeName\":\"VARCHAR\",\"IsCaseSensitive\":true,\"Name\":\"wednesday\"},{\"TypeName\":\"VARCHAR\",\"IsCaseSensitive\":true,\"Name\":\"thursday\"},{\"TypeName\":\"VARCHAR\",\"IsCaseSensitive\":true,\"Name\":\"friday\"},{\"TypeName\":\"VARCHAR\",\"IsCaseSensitive\":true,\"Name\":\"saturday\"},{\"TypeName\":\"VARCHAR\",\"IsCaseSensitive\":false,\"Name\":\"WEEKDAYS\"},{\"TypeName\":\"VARCHAR\",\"IsCaseSensitive\":true,\"Name\":\"meet_category\"}]}","{\"QUERY\":{\"COLUMNS\":[\"EMAIL\",\"FIRST_NAME\",\"LAST_NAME\",\"MIDDLE_NAME\",\"CATEGORY\",\"PRIMARY_IND\"],\"DATA\":[[\"dsbunch@ucdavis.edu\",\"David\",\"Bunch\",\"S\",\"01\",\"Y\"]]},\"QUERY_METADATA\":[{\"TypeName\":\"VARCHAR\",\"IsCaseSensitive\":true,\"Name\":\"email\"},{\"TypeName\":\"VARCHAR\",\"IsCaseSensitive\":true,\"Name\":\"first_name\"},{\"TypeName\":\"VARCHAR\",\"IsCaseSensitive\":true,\"Name\":\"last_name\"},{\"TypeName\":\"VARCHAR\",\"IsCaseSensitive\":true,\"Name\":\"middle_name\"},{\"TypeName\":\"VARCHAR\",\"IsCaseSensitive\":true,\"Name\":\"category\"},{\"TypeName\":\"VARCHAR\",\"IsCaseSensitive\":true,\"Name\":\"primary_ind\"}]}","","{\"QUERY\":{\"COLUMNS\":[\"SCRTEXT_SUBJ_CODE\",\"SCRTEXT_CRSE_NUMB\",\"SCRTEXT_EFF_TERM\",\"SCRTEXT_TEXT_CODE\",\"SCRTEXT_SEQNO\",\"SCRTEXT_TEXT\"],\"DATA\":[[\"MGP\",\"249\",\"201801\",\"A\",1.00000000000000000000,\"** OPEN TO STUDENTS IN THE MBA PROGRAM (SMBA, SMBE, SMBB) **\"]]},\"QUERY_METADATA\":[{\"TypeName\":\"VARCHAR\",\"IsCaseSensitive\":true,\"Name\":\"SCRTEXT_SUBJ_CODE\"},{\"TypeName\":\"VARCHAR\",\"IsCaseSensitive\":true,\"Name\":\"SCRTEXT_CRSE_NUMB\"},{\"TypeName\":\"VARCHAR\",\"IsCaseSensitive\":true,\"Name\":\"SCRTEXT_EFF_TERM\"},{\"TypeName\":\"VARCHAR\",\"IsCaseSensitive\":true,\"Name\":\"SCRTEXT_TEXT_CODE\"},{\"TypeName\":\"DECIMAL\",\"IsCaseSensitive\":false,\"Name\":\"SCRTEXT_SEQNO\"},{\"TypeName\":\"VARCHAR\",\"IsCaseSensitive\":true,\"Name\":\"SCRTEXT_TEXT\"}]}","",null,null,22,0,8],["R","20 Day Drop",0,"265",0,3,0,3,null,"Examines venture capital finance and the related practice of R&D finance. Goal is to apply finance tools and framework to the world of venture capital and financing of projects in high-growth industries.","43110",null,"February, 04 2019 00:00:00","","","","",null,0,"43110","MGB 205 or MGP 205 or MGT 205","001","MGP","Vent Cap/Fin of Innov","Vent Cap/Fin of Innov","Winter 19","{\"QUERY\":{\"COLUMNS\":[\"BLDG_DESC\",\"ROOM\",\"BEGIN_TIME\",\"END_TIME\",\"START_DATE\",\"END_DATE\",\"MEET_TYPE_CODE\",\"MEET_TYPE_DESC\",\"MEET_TYPE_DESC_SHORT\",\"SUNDAY\",\"MONDAY\",\"TUESDAY\",\"WEDNESDAY\",\"THURSDAY\",\"FRIDAY\",\"SATURDAY\",\"WEEKDAYS\",\"MEET_CATEGORY\"],\"DATA\":[[\"Sac. Med. Center\",null,null,null,\"January, 07 2019 00:00:00\",\"March, 15 2019 00:00:00\",\"B\",\"Lecture/Discussion\",\"LED\",null,null,null,null,null,null,\"S\",\"S\",\"01\"]]},\"QUERY_METADATA\":[{\"TypeName\":\"VARCHAR\",\"IsCaseSensitive\":true,\"Name\":\"bldg_desc\"},{\"TypeName\":\"VARCHAR\",\"IsCaseSensitive\":true,\"Name\":\"ROOM\"},{\"TypeName\":\"VARCHAR\",\"IsCaseSensitive\":true,\"Name\":\"begin_time\"},{\"TypeName\":\"VARCHAR\",\"IsCaseSensitive\":true,\"Name\":\"end_time\"},{\"TypeName\":\"TIMESTAMP\",\"IsCaseSensitive\":false,\"Name\":\"start_date\"},{\"TypeName\":\"TIMESTAMP\",\"IsCaseSensitive\":false,\"Name\":\"end_date\"},{\"TypeName\":\"VARCHAR\",\"IsCaseSensitive\":true,\"Name\":\"meet_type_code\"},{\"TypeName\":\"VARCHAR\",\"IsCaseSensitive\":true,\"Name\":\"meet_type_desc\"},{\"TypeName\":\"VARCHAR\",\"IsCaseSensitive\":true,\"Name\":\"meet_type_desc_short\"},{\"TypeName\":\"VARCHAR\",\"IsCaseSensitive\":true,\"Name\":\"sunday\"},{\"TypeName\":\"VARCHAR\",\"IsCaseSensitive\":true,\"Name\":\"monday\"},{\"TypeName\":\"VARCHAR\",\"IsCaseSensitive\":true,\"Name\":\"tuesday\"},{\"TypeName\":\"VARCHAR\",\"IsCaseSensitive\":true,\"Name\":\"wednesday\"},{\"TypeName\":\"VARCHAR\",\"IsCaseSensitive\":true,\"Name\":\"thursday\"},{\"TypeName\":\"VARCHAR\",\"IsCaseSensitive\":true,\"Name\":\"friday\"},{\"TypeName\":\"VARCHAR\",\"IsCaseSensitive\":true,\"Name\":\"saturday\"},{\"TypeName\":\"VARCHAR\",\"IsCaseSensitive\":false,\"Name\":\"WEEKDAYS\"},{\"TypeName\":\"VARCHAR\",\"IsCaseSensitive\":true,\"Name\":\"meet_category\"}]}","{\"QUERY\":{\"COLUMNS\":[\"EMAIL\",\"FIRST_NAME\",\"LAST_NAME\",\"MIDDLE_NAME\",\"CATEGORY\",\"PRIMARY_IND\"],\"DATA\":[[\"asyasuda@ucdavis.edu\",\"Ayako\",\"Yasuda\",null,\"01\",\"Y\"]]},\"QUERY_METADATA\":[{\"TypeName\":\"VARCHAR\",\"IsCaseSensitive\":true,\"Name\":\"email\"},{\"TypeName\":\"VARCHAR\",\"IsCaseSensitive\":true,\"Name\":\"first_name\"},{\"TypeName\":\"VARCHAR\",\"IsCaseSensitive\":true,\"Name\":\"last_name\"},{\"TypeName\":\"VARCHAR\",\"IsCaseSensitive\":true,\"Name\":\"middle_name\"},{\"TypeName\":\"VARCHAR\",\"IsCaseSensitive\":true,\"Name\":\"category\"},{\"TypeName\":\"VARCHAR\",\"IsCaseSensitive\":true,\"Name\":\"primary_ind\"}]}","","{\"QUERY\":{\"COLUMNS\":[\"SCRTEXT_SUBJ_CODE\",\"SCRTEXT_CRSE_NUMB\",\"SCRTEXT_EFF_TERM\",\"SCRTEXT_TEXT_CODE\",\"SCRTEXT_SEQNO\",\"SCRTEXT_TEXT\"],\"DATA\":[[\"MGP\",\"265\",\"201801\",\"A\",1.00000000000000000000,\"** OPEN TO STUDENTS IN THE MBA PROGRAM (SMBA, SMBE, SMBB) **\"]]},\"QUERY_METADATA\":[{\"TypeName\":\"VARCHAR\",\"IsCaseSensitive\":true,\"Name\":\"SCRTEXT_SUBJ_CODE\"},{\"TypeName\":\"VARCHAR\",\"IsCaseSensitive\":true,\"Name\":\"SCRTEXT_CRSE_NUMB\"},{\"TypeName\":\"VARCHAR\",\"IsCaseSensitive\":true,\"Name\":\"SCRTEXT_EFF_TERM\"},{\"TypeName\":\"VARCHAR\",\"IsCaseSensitive\":true,\"Name\":\"SCRTEXT_TEXT_CODE\"},{\"TypeName\":\"DECIMAL\",\"IsCaseSensitive\":false,\"Name\":\"SCRTEXT_SEQNO\"},{\"TypeName\":\"VARCHAR\",\"IsCaseSensitive\":true,\"Name\":\"SCRTEXT_TEXT\"}]}","",null,null,20,0,9],["E","10 Day Drop",0,"271",0,3,0,3,null,"Theoretical frameworks and associated techniques for using organizational design and cost management to achieve a sustainable, profitable cost structure. Topics include: target costing, process design for low cost, total cost of ownership, cost of customers, implementing structural change, and incentives.","43111",null,"January, 18 2019 00:00:00","","","","",null,0,"43111","MGT 202A or MGP 202A or MGB 202A","001","MGP","Strategic Cost Mgmt","Strategic Cost Mgmt","Winter 19","{\"QUERY\":{\"COLUMNS\":[\"BLDG_DESC\",\"ROOM\",\"BEGIN_TIME\",\"END_TIME\",\"START_DATE\",\"END_DATE\",\"MEET_TYPE_CODE\",\"MEET_TYPE_DESC\",\"MEET_TYPE_DESC_SHORT\",\"SUNDAY\",\"MONDAY\",\"TUESDAY\",\"WEDNESDAY\",\"THURSDAY\",\"FRIDAY\",\"SATURDAY\",\"WEEKDAYS\",\"MEET_CATEGORY\"],\"DATA\":[[\"Sac. Med. Center\",null,\"1800\",\"2100\",\"January, 07 2019 00:00:00\",\"March, 15 2019 00:00:00\",\"B\",\"Lecture/Discussion\",\"LED\",null,null,null,\"W\",null,null,null,\"W\",\"01\"]]},\"QUERY_METADATA\":[{\"TypeName\":\"VARCHAR\",\"IsCaseSensitive\":true,\"Name\":\"bldg_desc\"},{\"TypeName\":\"VARCHAR\",\"IsCaseSensitive\":true,\"Name\":\"ROOM\"},{\"TypeName\":\"VARCHAR\",\"IsCaseSensitive\":true,\"Name\":\"begin_time\"},{\"TypeName\":\"VARCHAR\",\"IsCaseSensitive\":true,\"Name\":\"end_time\"},{\"TypeName\":\"TIMESTAMP\",\"IsCaseSensitive\":false,\"Name\":\"start_date\"},{\"TypeName\":\"TIMESTAMP\",\"IsCaseSensitive\":false,\"Name\":\"end_date\"},{\"TypeName\":\"VARCHAR\",\"IsCaseSensitive\":true,\"Name\":\"meet_type_code\"},{\"TypeName\":\"VARCHAR\",\"IsCaseSensitive\":true,\"Name\":\"meet_type_desc\"},{\"TypeName\":\"VARCHAR\",\"IsCaseSensitive\":true,\"Name\":\"meet_type_desc_short\"},{\"TypeName\":\"VARCHAR\",\"IsCaseSensitive\":true,\"Name\":\"sunday\"},{\"TypeName\":\"VARCHAR\",\"IsCaseSensitive\":true,\"Name\":\"monday\"},{\"TypeName\":\"VARCHAR\",\"IsCaseSensitive\":true,\"Name\":\"tuesday\"},{\"TypeName\":\"VARCHAR\",\"IsCaseSensitive\":true,\"Name\":\"wednesday\"},{\"TypeName\":\"VARCHAR\",\"IsCaseSensitive\":true,\"Name\":\"thursday\"},{\"TypeName\":\"VARCHAR\",\"IsCaseSensitive\":true,\"Name\":\"friday\"},{\"TypeName\":\"VARCHAR\",\"IsCaseSensitive\":true,\"Name\":\"saturday\"},{\"TypeName\":\"VARCHAR\",\"IsCaseSensitive\":false,\"Name\":\"WEEKDAYS\"},{\"TypeName\":\"VARCHAR\",\"IsCaseSensitive\":true,\"Name\":\"meet_category\"}]}","{\"QUERY\":{\"COLUMNS\":[\"EMAIL\",\"FIRST_NAME\",\"LAST_NAME\",\"MIDDLE_NAME\",\"CATEGORY\",\"PRIMARY_IND\"],\"DATA\":[[\"swanderson@ucdavis.edu\",\"Shannon\",\"Anderson\",\"W\",\"01\",\"Y\"]]},\"QUERY_METADATA\":[{\"TypeName\":\"VARCHAR\",\"IsCaseSensitive\":true,\"Name\":\"email\"},{\"TypeName\":\"VARCHAR\",\"IsCaseSensitive\":true,\"Name\":\"first_name\"},{\"TypeName\":\"VARCHAR\",\"IsCaseSensitive\":true,\"Name\":\"last_name\"},{\"TypeName\":\"VARCHAR\",\"IsCaseSensitive\":true,\"Name\":\"middle_name\"},{\"TypeName\":\"VARCHAR\",\"IsCaseSensitive\":true,\"Name\":\"category\"},{\"TypeName\":\"VARCHAR\",\"IsCaseSensitive\":true,\"Name\":\"primary_ind\"}]}","","{\"QUERY\":{\"COLUMNS\":[\"SCRTEXT_SUBJ_CODE\",\"SCRTEXT_CRSE_NUMB\",\"SCRTEXT_EFF_TERM\",\"SCRTEXT_TEXT_CODE\",\"SCRTEXT_SEQNO\",\"SCRTEXT_TEXT\"],\"DATA\":[[\"MGP\",\"271\",\"201801\",\"A\",1.00000000000000000000,\"** OPEN TO STUDENTS IN THE MBA PROGRAM (SMBA, SMBE, SMBB) **\"]]},\"QUERY_METADATA\":[{\"TypeName\":\"VARCHAR\",\"IsCaseSensitive\":true,\"Name\":\"SCRTEXT_SUBJ_CODE\"},{\"TypeName\":\"VARCHAR\",\"IsCaseSensitive\":true,\"Name\":\"SCRTEXT_CRSE_NUMB\"},{\"TypeName\":\"VARCHAR\",\"IsCaseSensitive\":true,\"Name\":\"SCRTEXT_EFF_TERM\"},{\"TypeName\":\"VARCHAR\",\"IsCaseSensitive\":true,\"Name\":\"SCRTEXT_TEXT_CODE\"},{\"TypeName\":\"DECIMAL\",\"IsCaseSensitive\":false,\"Name\":\"SCRTEXT_SEQNO\"},{\"TypeName\":\"VARCHAR\",\"IsCaseSensitive\":true,\"Name\":\"SCRTEXT_TEXT\"}]}","",null,null,8,0,10],["E","10 Day Drop",0,"287",0,3,0,3,null,"Practical introduction to fundamental principles of database management systems and database marketing. Database design. SQL queries. Concepts of database marketing, data warehouse, data visualization and big data analytics.","43112",null,"January, 18 2019 00:00:00","","","","",null,0,"43112",null,"001","MGP","Bus Database & Marketing","Bus Database & Marketing","Winter 19","{\"QUERY\":{\"COLUMNS\":[\"BLDG_DESC\",\"ROOM\",\"BEGIN_TIME\",\"END_TIME\",\"START_DATE\",\"END_DATE\",\"MEET_TYPE_CODE\",\"MEET_TYPE_DESC\",\"MEET_TYPE_DESC_SHORT\",\"SUNDAY\",\"MONDAY\",\"TUESDAY\",\"WEDNESDAY\",\"THURSDAY\",\"FRIDAY\",\"SATURDAY\",\"WEEKDAYS\",\"MEET_CATEGORY\"],\"DATA\":[[\"Gallagher Hall\",\"2310\",\"1830\",\"2130\",\"January, 07 2019 00:00:00\",\"March, 15 2019 00:00:00\",\"A\",\"Lecture\",\"LEC\",null,\"M\",null,null,null,null,null,\"M\",\"01\"]]},\"QUERY_METADATA\":[{\"TypeName\":\"VARCHAR\",\"IsCaseSensitive\":true,\"Name\":\"bldg_desc\"},{\"TypeName\":\"VARCHAR\",\"IsCaseSensitive\":true,\"Name\":\"ROOM\"},{\"TypeName\":\"VARCHAR\",\"IsCaseSensitive\":true,\"Name\":\"begin_time\"},{\"TypeName\":\"VARCHAR\",\"IsCaseSensitive\":true,\"Name\":\"end_time\"},{\"TypeName\":\"TIMESTAMP\",\"IsCaseSensitive\":false,\"Name\":\"start_date\"},{\"TypeName\":\"TIMESTAMP\",\"IsCaseSensitive\":false,\"Name\":\"end_date\"},{\"TypeName\":\"VARCHAR\",\"IsCaseSensitive\":true,\"Name\":\"meet_type_code\"},{\"TypeName\":\"VARCHAR\",\"IsCaseSensitive\":true,\"Name\":\"meet_type_desc\"},{\"TypeName\":\"VARCHAR\",\"IsCaseSensitive\":true,\"Name\":\"meet_type_desc_short\"},{\"TypeName\":\"VARCHAR\",\"IsCaseSensitive\":true,\"Name\":\"sunday\"},{\"TypeName\":\"VARCHAR\",\"IsCaseSensitive\":true,\"Name\":\"monday\"},{\"TypeName\":\"VARCHAR\",\"IsCaseSensitive\":true,\"Name\":\"tuesday\"},{\"TypeName\":\"VARCHAR\",\"IsCaseSensitive\":true,\"Name\":\"wednesday\"},{\"TypeName\":\"VARCHAR\",\"IsCaseSensitive\":true,\"Name\":\"thursday\"},{\"TypeName\":\"VARCHAR\",\"IsCaseSensitive\":true,\"Name\":\"friday\"},{\"TypeName\":\"VARCHAR\",\"IsCaseSensitive\":true,\"Name\":\"saturday\"},{\"TypeName\":\"VARCHAR\",\"IsCaseSensitive\":false,\"Name\":\"WEEKDAYS\"},{\"TypeName\":\"VARCHAR\",\"IsCaseSensitive\":true,\"Name\":\"meet_category\"}]}","{\"QUERY\":{\"COLUMNS\":[\"EMAIL\",\"FIRST_NAME\",\"LAST_NAME\",\"MIDDLE_NAME\",\"CATEGORY\",\"PRIMARY_IND\"],\"DATA\":[[\"yiyang@ucdavis.edu\",\"Yinghui\",\"Yang\",null,\"01\",\"Y\"]]},\"QUERY_METADATA\":[{\"TypeName\":\"VARCHAR\",\"IsCaseSensitive\":true,\"Name\":\"email\"},{\"TypeName\":\"VARCHAR\",\"IsCaseSensitive\":true,\"Name\":\"first_name\"},{\"TypeName\":\"VARCHAR\",\"IsCaseSensitive\":true,\"Name\":\"last_name\"},{\"TypeName\":\"VARCHAR\",\"IsCaseSensitive\":true,\"Name\":\"middle_name\"},{\"TypeName\":\"VARCHAR\",\"IsCaseSensitive\":true,\"Name\":\"category\"},{\"TypeName\":\"VARCHAR\",\"IsCaseSensitive\":true,\"Name\":\"primary_ind\"}]}","","{\"QUERY\":{\"COLUMNS\":[\"SCRTEXT_SUBJ_CODE\",\"SCRTEXT_CRSE_NUMB\",\"SCRTEXT_EFF_TERM\",\"SCRTEXT_TEXT_CODE\",\"SCRTEXT_SEQNO\",\"SCRTEXT_TEXT\"],\"DATA\":[[\"MGP\",\"287\",\"201801\",\"A\",1.00000000000000000000,\"** OPEN TO STUDENTS IN THE MBA PROGRAM (SMBA, SMBE, SMBB) **\"]]},\"QUERY_METADATA\":[{\"TypeName\":\"VARCHAR\",\"IsCaseSensitive\":true,\"Name\":\"SCRTEXT_SUBJ_CODE\"},{\"TypeName\":\"VARCHAR\",\"IsCaseSensitive\":true,\"Name\":\"SCRTEXT_CRSE_NUMB\"},{\"TypeName\":\"VARCHAR\",\"IsCaseSensitive\":true,\"Name\":\"SCRTEXT_EFF_TERM\"},{\"TypeName\":\"VARCHAR\",\"IsCaseSensitive\":true,\"Name\":\"SCRTEXT_TEXT_CODE\"},{\"TypeName\":\"DECIMAL\",\"IsCaseSensitive\":false,\"Name\":\"SCRTEXT_SEQNO\"},{\"TypeName\":\"VARCHAR\",\"IsCaseSensitive\":true,\"Name\":\"SCRTEXT_TEXT\"}]}","",null,null,0,0,11],["R","20 Day Drop",0,"290",0,3,0,3,null,"Advanced topics in general management. Varied topics to cover more extensively issues discussed in courses 201A and 201B, or current business interest topics in fields of business writing, business communications, development, or workplace processes.","43113",null,"February, 04 2019 00:00:00","","","","",null,0,"43113","Completion of all first-year graduate courses at the Graduate School of Management or the equivalent.","001","MGP","Topics in Gen Mgmt","Topics in Gen Mgmt","Winter 19","{\"QUERY\":{\"COLUMNS\":[\"BLDG_DESC\",\"ROOM\",\"BEGIN_TIME\",\"END_TIME\",\"START_DATE\",\"END_DATE\",\"MEET_TYPE_CODE\",\"MEET_TYPE_DESC\",\"MEET_TYPE_DESC_SHORT\",\"SUNDAY\",\"MONDAY\",\"TUESDAY\",\"WEDNESDAY\",\"THURSDAY\",\"FRIDAY\",\"SATURDAY\",\"WEEKDAYS\",\"MEET_CATEGORY\"],\"DATA\":[[\"TBA\",\"TBA\",null,null,\"January, 07 2019 00:00:00\",\"March, 15 2019 00:00:00\",\"E\",\"Seminar\",\"SEM\",null,null,null,null,null,null,\"S\",\"S\",\"01\"]]},\"QUERY_METADATA\":[{\"TypeName\":\"VARCHAR\",\"IsCaseSensitive\":true,\"Name\":\"bldg_desc\"},{\"TypeName\":\"VARCHAR\",\"IsCaseSensitive\":true,\"Name\":\"ROOM\"},{\"TypeName\":\"VARCHAR\",\"IsCaseSensitive\":true,\"Name\":\"begin_time\"},{\"TypeName\":\"VARCHAR\",\"IsCaseSensitive\":true,\"Name\":\"end_time\"},{\"TypeName\":\"TIMESTAMP\",\"IsCaseSensitive\":false,\"Name\":\"start_date\"},{\"TypeName\":\"TIMESTAMP\",\"IsCaseSensitive\":false,\"Name\":\"end_date\"},{\"TypeName\":\"VARCHAR\",\"IsCaseSensitive\":true,\"Name\":\"meet_type_code\"},{\"TypeName\":\"VARCHAR\",\"IsCaseSensitive\":true,\"Name\":\"meet_type_desc\"},{\"TypeName\":\"VARCHAR\",\"IsCaseSensitive\":true,\"Name\":\"meet_type_desc_short\"},{\"TypeName\":\"VARCHAR\",\"IsCaseSensitive\":true,\"Name\":\"sunday\"},{\"TypeName\":\"VARCHAR\",\"IsCaseSensitive\":true,\"Name\":\"monday\"},{\"TypeName\":\"VARCHAR\",\"IsCaseSensitive\":true,\"Name\":\"tuesday\"},{\"TypeName\":\"VARCHAR\",\"IsCaseSensitive\":true,\"Name\":\"wednesday\"},{\"TypeName\":\"VARCHAR\",\"IsCaseSensitive\":true,\"Name\":\"thursday\"},{\"TypeName\":\"VARCHAR\",\"IsCaseSensitive\":true,\"Name\":\"friday\"},{\"TypeName\":\"VARCHAR\",\"IsCaseSensitive\":true,\"Name\":\"saturday\"},{\"TypeName\":\"VARCHAR\",\"IsCaseSensitive\":false,\"Name\":\"WEEKDAYS\"},{\"TypeName\":\"VARCHAR\",\"IsCaseSensitive\":true,\"Name\":\"meet_category\"}]}","{\"QUERY\":{\"COLUMNS\":[\"EMAIL\",\"FIRST_NAME\",\"LAST_NAME\",\"MIDDLE_NAME\",\"CATEGORY\",\"PRIMARY_IND\"],\"DATA\":[[\"mrangwala@ucdavis.edu\",\"Mehul\",\"Rangwala\",null,\"01\",\"Y\"]]},\"QUERY_METADATA\":[{\"TypeName\":\"VARCHAR\",\"IsCaseSensitive\":true,\"Name\":\"email\"},{\"TypeName\":\"VARCHAR\",\"IsCaseSensitive\":true,\"Name\":\"first_name\"},{\"TypeName\":\"VARCHAR\",\"IsCaseSensitive\":true,\"Name\":\"last_name\"},{\"TypeName\":\"VARCHAR\",\"IsCaseSensitive\":true,\"Name\":\"middle_name\"},{\"TypeName\":\"VARCHAR\",\"IsCaseSensitive\":true,\"Name\":\"category\"},{\"TypeName\":\"VARCHAR\",\"IsCaseSensitive\":true,\"Name\":\"primary_ind\"}]}","","{\"QUERY\":{\"COLUMNS\":[\"SCRTEXT_SUBJ_CODE\",\"SCRTEXT_CRSE_NUMB\",\"SCRTEXT_EFF_TERM\",\"SCRTEXT_TEXT_CODE\",\"SCRTEXT_SEQNO\",\"SCRTEXT_TEXT\"],\"DATA\":[[\"MGP\",\"290\",\"201801\",\"A\",1.00000000000000000000,\"** OPEN TO STUDENTS IN THE MBA PROGRAM (SMBA, SMBE, SMBB) **\"]]},\"QUERY_METADATA\":[{\"TypeName\":\"VARCHAR\",\"IsCaseSensitive\":true,\"Name\":\"SCRTEXT_SUBJ_CODE\"},{\"TypeName\":\"VARCHAR\",\"IsCaseSensitive\":true,\"Name\":\"SCRTEXT_CRSE_NUMB\"},{\"TypeName\":\"VARCHAR\",\"IsCaseSensitive\":true,\"Name\":\"SCRTEXT_EFF_TERM\"},{\"TypeName\":\"VARCHAR\",\"IsCaseSensitive\":true,\"Name\":\"SCRTEXT_TEXT_CODE\"},{\"TypeName\":\"DECIMAL\",\"IsCaseSensitive\":false,\"Name\":\"SCRTEXT_SEQNO\"},{\"TypeName\":\"VARCHAR\",\"IsCaseSensitive\":true,\"Name\":\"SCRTEXT_TEXT\"}]}","",null,null,29,0,12],["R","20 Day Drop",0,"290",0,3,0,3,null,"Advanced topics in general management. Varied topics to cover more extensively issues discussed in courses 201A and 201B, or current business interest topics in fields of business writing, business communications, development, or workplace processes.","43114",null,"February, 04 2019 00:00:00","","","","",null,0,"43114","Completion of all first-year graduate courses at the Graduate School of Management or the equivalent.","002","MGP","Topics in Gen Mgmt","Topics in Gen Mgmt","Winter 19","{\"QUERY\":{\"COLUMNS\":[\"BLDG_DESC\",\"ROOM\",\"BEGIN_TIME\",\"END_TIME\",\"START_DATE\",\"END_DATE\",\"MEET_TYPE_CODE\",\"MEET_TYPE_DESC\",\"MEET_TYPE_DESC_SHORT\",\"SUNDAY\",\"MONDAY\",\"TUESDAY\",\"WEDNESDAY\",\"THURSDAY\",\"FRIDAY\",\"SATURDAY\",\"WEEKDAYS\",\"MEET_CATEGORY\"],\"DATA\":[[\"TBA\",\"TBA\",null,null,\"January, 07 2019 00:00:00\",\"March, 15 2019 00:00:00\",\"E\",\"Seminar\",\"SEM\",null,null,null,null,null,null,\"S\",\"S\",\"01\"]]},\"QUERY_METADATA\":[{\"TypeName\":\"VARCHAR\",\"IsCaseSensitive\":true,\"Name\":\"bldg_desc\"},{\"TypeName\":\"VARCHAR\",\"IsCaseSensitive\":true,\"Name\":\"ROOM\"},{\"TypeName\":\"VARCHAR\",\"IsCaseSensitive\":true,\"Name\":\"begin_time\"},{\"TypeName\":\"VARCHAR\",\"IsCaseSensitive\":true,\"Name\":\"end_time\"},{\"TypeName\":\"TIMESTAMP\",\"IsCaseSensitive\":false,\"Name\":\"start_date\"},{\"TypeName\":\"TIMESTAMP\",\"IsCaseSensitive\":false,\"Name\":\"end_date\"},{\"TypeName\":\"VARCHAR\",\"IsCaseSensitive\":true,\"Name\":\"meet_type_code\"},{\"TypeName\":\"VARCHAR\",\"IsCaseSensitive\":true,\"Name\":\"meet_type_desc\"},{\"TypeName\":\"VARCHAR\",\"IsCaseSensitive\":true,\"Name\":\"meet_type_desc_short\"},{\"TypeName\":\"VARCHAR\",\"IsCaseSensitive\":true,\"Name\":\"sunday\"},{\"TypeName\":\"VARCHAR\",\"IsCaseSensitive\":true,\"Name\":\"monday\"},{\"TypeName\":\"VARCHAR\",\"IsCaseSensitive\":true,\"Name\":\"tuesday\"},{\"TypeName\":\"VARCHAR\",\"IsCaseSensitive\":true,\"Name\":\"wednesday\"},{\"TypeName\":\"VARCHAR\",\"IsCaseSensitive\":true,\"Name\":\"thursday\"},{\"TypeName\":\"VARCHAR\",\"IsCaseSensitive\":true,\"Name\":\"friday\"},{\"TypeName\":\"VARCHAR\",\"IsCaseSensitive\":true,\"Name\":\"saturday\"},{\"TypeName\":\"VARCHAR\",\"IsCaseSensitive\":false,\"Name\":\"WEEKDAYS\"},{\"TypeName\":\"VARCHAR\",\"IsCaseSensitive\":true,\"Name\":\"meet_category\"}]}","{\"QUERY\":{\"COLUMNS\":[\"EMAIL\",\"FIRST_NAME\",\"LAST_NAME\",\"MIDDLE_NAME\",\"CATEGORY\",\"PRIMARY_IND\"],\"DATA\":[[\"mrangwala@ucdavis.edu\",\"Mehul\",\"Rangwala\",null,\"01\",\"Y\"]]},\"QUERY_METADATA\":[{\"TypeName\":\"VARCHAR\",\"IsCaseSensitive\":true,\"Name\":\"email\"},{\"TypeName\":\"VARCHAR\",\"IsCaseSensitive\":true,\"Name\":\"first_name\"},{\"TypeName\":\"VARCHAR\",\"IsCaseSensitive\":true,\"Name\":\"last_name\"},{\"TypeName\":\"VARCHAR\",\"IsCaseSensitive\":true,\"Name\":\"middle_name\"},{\"TypeName\":\"VARCHAR\",\"IsCaseSensitive\":true,\"Name\":\"category\"},{\"TypeName\":\"VARCHAR\",\"IsCaseSensitive\":true,\"Name\":\"primary_ind\"}]}","","{\"QUERY\":{\"COLUMNS\":[\"SCRTEXT_SUBJ_CODE\",\"SCRTEXT_CRSE_NUMB\",\"SCRTEXT_EFF_TERM\",\"SCRTEXT_TEXT_CODE\",\"SCRTEXT_SEQNO\",\"SCRTEXT_TEXT\"],\"DATA\":[[\"MGP\",\"290\",\"201801\",\"A\",1.00000000000000000000,\"** OPEN TO STUDENTS IN THE MBA PROGRAM (SMBA, SMBE, SMBB) **\"]]},\"QUERY_METADATA\":[{\"TypeName\":\"VARCHAR\",\"IsCaseSensitive\":true,\"Name\":\"SCRTEXT_SUBJ_CODE\"},{\"TypeName\":\"VARCHAR\",\"IsCaseSensitive\":true,\"Name\":\"SCRTEXT_CRSE_NUMB\"},{\"TypeName\":\"VARCHAR\",\"IsCaseSensitive\":true,\"Name\":\"SCRTEXT_EFF_TERM\"},{\"TypeName\":\"VARCHAR\",\"IsCaseSensitive\":true,\"Name\":\"SCRTEXT_TEXT_CODE\"},{\"TypeName\":\"DECIMAL\",\"IsCaseSensitive\":false,\"Name\":\"SCRTEXT_SEQNO\"},{\"TypeName\":\"VARCHAR\",\"IsCaseSensitive\":true,\"Name\":\"SCRTEXT_TEXT\"}]}","",null,null,6,0,13],["E","10 Day Drop",0,"297",0,3,0,3,null,"Broader environment in which U.S. firms and their foreign competitors operate. Integration of material from other topics courses (marketing, strategy, finance, accounting, information technology, technology management) into the international setting. May be repeated for credit.","43120",null,"January, 18 2019 00:00:00","","","","",null,0,"43120","Completion of all first-year graduate courses at the Graduate School of Management or the equivalent.","001","MGP","Topics in Internat'l Mgt","Topics in Internat'l Mgt","Winter 19","{\"QUERY\":{\"COLUMNS\":[\"BLDG_DESC\",\"ROOM\",\"BEGIN_TIME\",\"END_TIME\",\"START_DATE\",\"END_DATE\",\"MEET_TYPE_CODE\",\"MEET_TYPE_DESC\",\"MEET_TYPE_DESC_SHORT\",\"SUNDAY\",\"MONDAY\",\"TUESDAY\",\"WEDNESDAY\",\"THURSDAY\",\"FRIDAY\",\"SATURDAY\",\"WEEKDAYS\",\"MEET_CATEGORY\"],\"DATA\":[[\"TBA\",\"TBA\",null,null,\"January, 07 2019 00:00:00\",\"March, 15 2019 00:00:00\",\"E\",\"Seminar\",\"SEM\",\"U\",null,null,null,null,null,null,\"U\",\"01\"],[\"TBA\",\"TBA\",null,null,\"January, 07 2019 00:00:00\",\"March, 15 2019 00:00:00\",\"E\",\"Seminar\",\"SEM\",null,null,null,null,null,null,null,\"\",\"02\"]]},\"QUERY_METADATA\":[{\"TypeName\":\"VARCHAR\",\"IsCaseSensitive\":true,\"Name\":\"bldg_desc\"},{\"TypeName\":\"VARCHAR\",\"IsCaseSensitive\":true,\"Name\":\"ROOM\"},{\"TypeName\":\"VARCHAR\",\"IsCaseSensitive\":true,\"Name\":\"begin_time\"},{\"TypeName\":\"VARCHAR\",\"IsCaseSensitive\":true,\"Name\":\"end_time\"},{\"TypeName\":\"TIMESTAMP\",\"IsCaseSensitive\":false,\"Name\":\"start_date\"},{\"TypeName\":\"TIMESTAMP\",\"IsCaseSensitive\":false,\"Name\":\"end_date\"},{\"TypeName\":\"VARCHAR\",\"IsCaseSensitive\":true,\"Name\":\"meet_type_code\"},{\"TypeName\":\"VARCHAR\",\"IsCaseSensitive\":true,\"Name\":\"meet_type_desc\"},{\"TypeName\":\"VARCHAR\",\"IsCaseSensitive\":true,\"Name\":\"meet_type_desc_short\"},{\"TypeName\":\"VARCHAR\",\"IsCaseSensitive\":true,\"Name\":\"sunday\"},{\"TypeName\":\"VARCHAR\",\"IsCaseSensitive\":true,\"Name\":\"monday\"},{\"TypeName\":\"VARCHAR\",\"IsCaseSensitive\":true,\"Name\":\"tuesday\"},{\"TypeName\":\"VARCHAR\",\"IsCaseSensitive\":true,\"Name\":\"wednesday\"},{\"TypeName\":\"VARCHAR\",\"IsCaseSensitive\":true,\"Name\":\"thursday\"},{\"TypeName\":\"VARCHAR\",\"IsCaseSensitive\":true,\"Name\":\"friday\"},{\"TypeName\":\"VARCHAR\",\"IsCaseSensitive\":true,\"Name\":\"saturday\"},{\"TypeName\":\"VARCHAR\",\"IsCaseSensitive\":false,\"Name\":\"WEEKDAYS\"},{\"TypeName\":\"VARCHAR\",\"IsCaseSensitive\":true,\"Name\":\"meet_category\"}]}","{\"QUERY\":{\"COLUMNS\":[\"EMAIL\",\"FIRST_NAME\",\"LAST_NAME\",\"MIDDLE_NAME\",\"CATEGORY\",\"PRIMARY_IND\"],\"DATA\":[[\"staherian@ucdavis.edu\",\"Sezaneh\",\"Taherian\",null,\"01\",\"Y\"]]},\"QUERY_METADATA\":[{\"TypeName\":\"VARCHAR\",\"IsCaseSensitive\":true,\"Name\":\"email\"},{\"TypeName\":\"VARCHAR\",\"IsCaseSensitive\":true,\"Name\":\"first_name\"},{\"TypeName\":\"VARCHAR\",\"IsCaseSensitive\":true,\"Name\":\"last_name\"},{\"TypeName\":\"VARCHAR\",\"IsCaseSensitive\":true,\"Name\":\"middle_name\"},{\"TypeName\":\"VARCHAR\",\"IsCaseSensitive\":true,\"Name\":\"category\"},{\"TypeName\":\"VARCHAR\",\"IsCaseSensitive\":true,\"Name\":\"primary_ind\"}]}","","{\"QUERY\":{\"COLUMNS\":[\"SCRTEXT_SUBJ_CODE\",\"SCRTEXT_CRSE_NUMB\",\"SCRTEXT_EFF_TERM\",\"SCRTEXT_TEXT_CODE\",\"SCRTEXT_SEQNO\",\"SCRTEXT_TEXT\"],\"DATA\":[[\"MGP\",\"297\",\"201801\",\"A\",1.00000000000000000000,\"** OPEN TO STUDENTS IN THE MBA PROGRAM (SMBA, SMBE, SMBB) **\"]]},\"QUERY_METADATA\":[{\"TypeName\":\"VARCHAR\",\"IsCaseSensitive\":true,\"Name\":\"SCRTEXT_SUBJ_CODE\"},{\"TypeName\":\"VARCHAR\",\"IsCaseSensitive\":true,\"Name\":\"SCRTEXT_CRSE_NUMB\"},{\"TypeName\":\"VARCHAR\",\"IsCaseSensitive\":true,\"Name\":\"SCRTEXT_EFF_TERM\"},{\"TypeName\":\"VARCHAR\",\"IsCaseSensitive\":true,\"Name\":\"SCRTEXT_TEXT_CODE\"},{\"TypeName\":\"DECIMAL\",\"IsCaseSensitive\":false,\"Name\":\"SCRTEXT_SEQNO\"},{\"TypeName\":\"VARCHAR\",\"IsCaseSensitive\":true,\"Name\":\"SCRTEXT_TEXT\"}]}","",null,null,0,0,14],["R","20 Day Drop",0,"412",0,1,0,1,null,"Basic concepts of international marketing. Understanding and managing heterogeneous, dynamic, and interdependent environments across countries. How to develop and implement an international marketing strategy: where and how to compete, how to adapt to your marketing mix.","43125",null,"February, 04 2019 00:00:00","","","","",null,0,"43125",null,"001","MGP","International Marketing","International Marketing","Winter 19","{\"QUERY\":{\"COLUMNS\":[\"BLDG_DESC\",\"ROOM\",\"BEGIN_TIME\",\"END_TIME\",\"START_DATE\",\"END_DATE\",\"MEET_TYPE_CODE\",\"MEET_TYPE_DESC\",\"MEET_TYPE_DESC_SHORT\",\"SUNDAY\",\"MONDAY\",\"TUESDAY\",\"WEDNESDAY\",\"THURSDAY\",\"FRIDAY\",\"SATURDAY\",\"WEEKDAYS\",\"MEET_CATEGORY\"],\"DATA\":[[\"TBA\",\"TBA\",null,null,\"January, 07 2019 00:00:00\",\"March, 15 2019 00:00:00\",\"B\",\"Lecture/Discussion\",\"LED\",\"U\",null,null,null,null,null,null,\"U\",\"01\"],[\"TBA\",\"TBA\",null,null,\"January, 07 2019 00:00:00\",\"March, 15 2019 00:00:00\",\"B\",\"Lecture/Discussion\",\"LED\",null,null,null,null,null,null,null,\"\",\"02\"]]},\"QUERY_METADATA\":[{\"TypeName\":\"VARCHAR\",\"IsCaseSensitive\":true,\"Name\":\"bldg_desc\"},{\"TypeName\":\"VARCHAR\",\"IsCaseSensitive\":true,\"Name\":\"ROOM\"},{\"TypeName\":\"VARCHAR\",\"IsCaseSensitive\":true,\"Name\":\"begin_time\"},{\"TypeName\":\"VARCHAR\",\"IsCaseSensitive\":true,\"Name\":\"end_time\"},{\"TypeName\":\"TIMESTAMP\",\"IsCaseSensitive\":false,\"Name\":\"start_date\"},{\"TypeName\":\"TIMESTAMP\",\"IsCaseSensitive\":false,\"Name\":\"end_date\"},{\"TypeName\":\"VARCHAR\",\"IsCaseSensitive\":true,\"Name\":\"meet_type_code\"},{\"TypeName\":\"VARCHAR\",\"IsCaseSensitive\":true,\"Name\":\"meet_type_desc\"},{\"TypeName\":\"VARCHAR\",\"IsCaseSensitive\":true,\"Name\":\"meet_type_desc_short\"},{\"TypeName\":\"VARCHAR\",\"IsCaseSensitive\":true,\"Name\":\"sunday\"},{\"TypeName\":\"VARCHAR\",\"IsCaseSensitive\":true,\"Name\":\"monday\"},{\"TypeName\":\"VARCHAR\",\"IsCaseSensitive\":true,\"Name\":\"tuesday\"},{\"TypeName\":\"VARCHAR\",\"IsCaseSensitive\":true,\"Name\":\"wednesday\"},{\"TypeName\":\"VARCHAR\",\"IsCaseSensitive\":true,\"Name\":\"thursday\"},{\"TypeName\":\"VARCHAR\",\"IsCaseSensitive\":true,\"Name\":\"friday\"},{\"TypeName\":\"VARCHAR\",\"IsCaseSensitive\":true,\"Name\":\"saturday\"},{\"TypeName\":\"VARCHAR\",\"IsCaseSensitive\":false,\"Name\":\"WEEKDAYS\"},{\"TypeName\":\"VARCHAR\",\"IsCaseSensitive\":true,\"Name\":\"meet_category\"}]}","{\"QUERY\":{\"COLUMNS\":[\"EMAIL\",\"FIRST_NAME\",\"LAST_NAME\",\"MIDDLE_NAME\",\"CATEGORY\",\"PRIMARY_IND\"],\"DATA\":[[\"kpeters@ucdavis.edu\",\"Kay\",\"Peters\",null,\"01\",\"Y\"]]},\"QUERY_METADATA\":[{\"TypeName\":\"VARCHAR\",\"IsCaseSensitive\":true,\"Name\":\"email\"},{\"TypeName\":\"VARCHAR\",\"IsCaseSensitive\":true,\"Name\":\"first_name\"},{\"TypeName\":\"VARCHAR\",\"IsCaseSensitive\":true,\"Name\":\"last_name\"},{\"TypeName\":\"VARCHAR\",\"IsCaseSensitive\":true,\"Name\":\"middle_name\"},{\"TypeName\":\"VARCHAR\",\"IsCaseSensitive\":true,\"Name\":\"category\"},{\"TypeName\":\"VARCHAR\",\"IsCaseSensitive\":true,\"Name\":\"primary_ind\"}]}","","{\"QUERY\":{\"COLUMNS\":[\"SCRTEXT_SUBJ_CODE\",\"SCRTEXT_CRSE_NUMB\",\"SCRTEXT_EFF_TERM\",\"SCRTEXT_TEXT_CODE\",\"SCRTEXT_SEQNO\",\"SCRTEXT_TEXT\"],\"DATA\":[[\"MGP\",\"412\",\"201801\",\"A\",1.00000000000000000000,\"** OPEN TO STUDENTS IN THE MBA PROGRAM (SMBA, SMBE, SMBB) **\"]]},\"QUERY_METADATA\":[{\"TypeName\":\"VARCHAR\",\"IsCaseSensitive\":true,\"Name\":\"SCRTEXT_SUBJ_CODE\"},{\"TypeName\":\"VARCHAR\",\"IsCaseSensitive\":true,\"Name\":\"SCRTEXT_CRSE_NUMB\"},{\"TypeName\":\"VARCHAR\",\"IsCaseSensitive\":true,\"Name\":\"SCRTEXT_EFF_TERM\"},{\"TypeName\":\"VARCHAR\",\"IsCaseSensitive\":true,\"Name\":\"SCRTEXT_TEXT_CODE\"},{\"TypeName\":\"DECIMAL\",\"IsCaseSensitive\":false,\"Name\":\"SCRTEXT_SEQNO\"},{\"TypeName\":\"VARCHAR\",\"IsCaseSensitive\":true,\"Name\":\"SCRTEXT_TEXT\"}]}","",null,null,10,0,15],["R","20 Day Drop",0,"429",0,1,0,1,null,"Course will discuss the fundamentals of fraud detection and prevention in the workplace. Students will learn the major schemes involving workplace fraud, how management can detect fraud and what policies and procedures can be implemented to prevent fraud.","43126",null,"February, 04 2019 00:00:00","","","","",null,0,"43126",null,"001","MGP","Detection and Prevention","Detection and Prevention","Winter 19","{\"QUERY\":{\"COLUMNS\":[\"BLDG_DESC\",\"ROOM\",\"BEGIN_TIME\",\"END_TIME\",\"START_DATE\",\"END_DATE\",\"MEET_TYPE_CODE\",\"MEET_TYPE_DESC\",\"MEET_TYPE_DESC_SHORT\",\"SUNDAY\",\"MONDAY\",\"TUESDAY\",\"WEDNESDAY\",\"THURSDAY\",\"FRIDAY\",\"SATURDAY\",\"WEEKDAYS\",\"MEET_CATEGORY\"],\"DATA\":[[\"TBA\",\"TBA\",null,null,\"January, 07 2019 00:00:00\",\"March, 15 2019 00:00:00\",\"A\",\"Lecture\",\"LEC\",\"U\",null,null,null,null,null,null,\"U\",\"01\"]]},\"QUERY_METADATA\":[{\"TypeName\":\"VARCHAR\",\"IsCaseSensitive\":true,\"Name\":\"bldg_desc\"},{\"TypeName\":\"VARCHAR\",\"IsCaseSensitive\":true,\"Name\":\"ROOM\"},{\"TypeName\":\"VARCHAR\",\"IsCaseSensitive\":true,\"Name\":\"begin_time\"},{\"TypeName\":\"VARCHAR\",\"IsCaseSensitive\":true,\"Name\":\"end_time\"},{\"TypeName\":\"TIMESTAMP\",\"IsCaseSensitive\":false,\"Name\":\"start_date\"},{\"TypeName\":\"TIMESTAMP\",\"IsCaseSensitive\":false,\"Name\":\"end_date\"},{\"TypeName\":\"VARCHAR\",\"IsCaseSensitive\":true,\"Name\":\"meet_type_code\"},{\"TypeName\":\"VARCHAR\",\"IsCaseSensitive\":true,\"Name\":\"meet_type_desc\"},{\"TypeName\":\"VARCHAR\",\"IsCaseSensitive\":true,\"Name\":\"meet_type_desc_short\"},{\"TypeName\":\"VARCHAR\",\"IsCaseSensitive\":true,\"Name\":\"sunday\"},{\"TypeName\":\"VARCHAR\",\"IsCaseSensitive\":true,\"Name\":\"monday\"},{\"TypeName\":\"VARCHAR\",\"IsCaseSensitive\":true,\"Name\":\"tuesday\"},{\"TypeName\":\"VARCHAR\",\"IsCaseSensitive\":true,\"Name\":\"wednesday\"},{\"TypeName\":\"VARCHAR\",\"IsCaseSensitive\":true,\"Name\":\"thursday\"},{\"TypeName\":\"VARCHAR\",\"IsCaseSensitive\":true,\"Name\":\"friday\"},{\"TypeName\":\"VARCHAR\",\"IsCaseSensitive\":true,\"Name\":\"saturday\"},{\"TypeName\":\"VARCHAR\",\"IsCaseSensitive\":false,\"Name\":\"WEEKDAYS\"},{\"TypeName\":\"VARCHAR\",\"IsCaseSensitive\":true,\"Name\":\"meet_category\"}]}","{\"QUERY\":{\"COLUMNS\":[\"EMAIL\",\"FIRST_NAME\",\"LAST_NAME\",\"MIDDLE_NAME\",\"CATEGORY\",\"PRIMARY_IND\"],\"DATA\":[[\"nabriscoe@ucdavis.edu\",\"Nicholas\",\"Briscoe\",\"Andrew\",\"01\",\"Y\"]]},\"QUERY_METADATA\":[{\"TypeName\":\"VARCHAR\",\"IsCaseSensitive\":true,\"Name\":\"email\"},{\"TypeName\":\"VARCHAR\",\"IsCaseSensitive\":true,\"Name\":\"first_name\"},{\"TypeName\":\"VARCHAR\",\"IsCaseSensitive\":true,\"Name\":\"last_name\"},{\"TypeName\":\"VARCHAR\",\"IsCaseSensitive\":true,\"Name\":\"middle_name\"},{\"TypeName\":\"VARCHAR\",\"IsCaseSensitive\":true,\"Name\":\"category\"},{\"TypeName\":\"VARCHAR\",\"IsCaseSensitive\":true,\"Name\":\"primary_ind\"}]}","","{\"QUERY\":{\"COLUMNS\":[\"SCRTEXT_SUBJ_CODE\",\"SCRTEXT_CRSE_NUMB\",\"SCRTEXT_EFF_TERM\",\"SCRTEXT_TEXT_CODE\",\"SCRTEXT_SEQNO\",\"SCRTEXT_TEXT\"],\"DATA\":[[\"MGP\",\"429\",\"201901\",\"A\",1.00000000000000000000,\"** OPEN TO STUDENTS IN THE MBA PROGRAM (SMBE, SMBB, SMBA) **\"]]},\"QUERY_METADATA\":[{\"TypeName\":\"VARCHAR\",\"IsCaseSensitive\":true,\"Name\":\"SCRTEXT_SUBJ_CODE\"},{\"TypeName\":\"VARCHAR\",\"IsCaseSensitive\":true,\"Name\":\"SCRTEXT_CRSE_NUMB\"},{\"TypeName\":\"VARCHAR\",\"IsCaseSensitive\":true,\"Name\":\"SCRTEXT_EFF_TERM\"},{\"TypeName\":\"VARCHAR\",\"IsCaseSensitive\":true,\"Name\":\"SCRTEXT_TEXT_CODE\"},{\"TypeName\":\"DECIMAL\",\"IsCaseSensitive\":false,\"Name\":\"SCRTEXT_SEQNO\"},{\"TypeName\":\"VARCHAR\",\"IsCaseSensitive\":true,\"Name\":\"SCRTEXT_TEXT\"}]}","",null,null,12,0,16],["R","20 Day Drop",1,"498",12,1,12,1,"TO","Provides the opportunity for students to gain experience in applying business methodologies previously acquired in other GSM courses.","@",null,"February, 04 2019 00:00:00","","","","",null,1,"084BCFC8EA","Consent of Instructor.  Sponsorship of a GSM Academic Senate faculty member; approval of graduate advisor.","002","MGP","Dir Grp Mgmt Prac","Dir Grp Mgmt Prac","Winter 19","{\"QUERY\":{\"COLUMNS\":[\"BLDG_DESC\",\"ROOM\",\"BEGIN_TIME\",\"END_TIME\",\"START_DATE\",\"END_DATE\",\"MEET_TYPE_CODE\",\"MEET_TYPE_DESC\",\"MEET_TYPE_DESC_SHORT\",\"SUNDAY\",\"MONDAY\",\"TUESDAY\",\"WEDNESDAY\",\"THURSDAY\",\"FRIDAY\",\"SATURDAY\",\"WEEKDAYS\",\"MEET_CATEGORY\"],\"DATA\":[[\"TBA\",\"TBA\",null,null,\"January, 07 2019 00:00:00\",\"March, 15 2019 00:00:00\",\"V\",\"Variable\",\"VAR\",null,null,null,null,null,null,null,\"\",\"01\"]]},\"QUERY_METADATA\":[{\"TypeName\":\"VARCHAR\",\"IsCaseSensitive\":true,\"Name\":\"bldg_desc\"},{\"TypeName\":\"VARCHAR\",\"IsCaseSensitive\":true,\"Name\":\"ROOM\"},{\"TypeName\":\"VARCHAR\",\"IsCaseSensitive\":true,\"Name\":\"begin_time\"},{\"TypeName\":\"VARCHAR\",\"IsCaseSensitive\":true,\"Name\":\"end_time\"},{\"TypeName\":\"TIMESTAMP\",\"IsCaseSensitive\":false,\"Name\":\"start_date\"},{\"TypeName\":\"TIMESTAMP\",\"IsCaseSensitive\":false,\"Name\":\"end_date\"},{\"TypeName\":\"VARCHAR\",\"IsCaseSensitive\":true,\"Name\":\"meet_type_code\"},{\"TypeName\":\"VARCHAR\",\"IsCaseSensitive\":true,\"Name\":\"meet_type_desc\"},{\"TypeName\":\"VARCHAR\",\"IsCaseSensitive\":true,\"Name\":\"meet_type_desc_short\"},{\"TypeName\":\"VARCHAR\",\"IsCaseSensitive\":true,\"Name\":\"sunday\"},{\"TypeName\":\"VARCHAR\",\"IsCaseSensitive\":true,\"Name\":\"monday\"},{\"TypeName\":\"VARCHAR\",\"IsCaseSensitive\":true,\"Name\":\"tuesday\"},{\"TypeName\":\"VARCHAR\",\"IsCaseSensitive\":true,\"Name\":\"wednesday\"},{\"TypeName\":\"VARCHAR\",\"IsCaseSensitive\":true,\"Name\":\"thursday\"},{\"TypeName\":\"VARCHAR\",\"IsCaseSensitive\":true,\"Name\":\"friday\"},{\"TypeName\":\"VARCHAR\",\"IsCaseSensitive\":true,\"Name\":\"saturday\"},{\"TypeName\":\"VARCHAR\",\"IsCaseSensitive\":false,\"Name\":\"WEEKDAYS\"},{\"TypeName\":\"VARCHAR\",\"IsCaseSensitive\":true,\"Name\":\"meet_category\"}]}","{\"QUERY\":{\"COLUMNS\":[\"EMAIL\",\"FIRST_NAME\",\"LAST_NAME\",\"MIDDLE_NAME\",\"CATEGORY\",\"PRIMARY_IND\"],\"DATA\":[[\"aaravind@ucdavis.edu\",\"Ashwin\",\"Aravindakshan\",null,\"01\",\"Y\"]]},\"QUERY_METADATA\":[{\"TypeName\":\"VARCHAR\",\"IsCaseSensitive\":true,\"Name\":\"email\"},{\"TypeName\":\"VARCHAR\",\"IsCaseSensitive\":true,\"Name\":\"first_name\"},{\"TypeName\":\"VARCHAR\",\"IsCaseSensitive\":true,\"Name\":\"last_name\"},{\"TypeName\":\"VARCHAR\",\"IsCaseSensitive\":true,\"Name\":\"middle_name\"},{\"TypeName\":\"VARCHAR\",\"IsCaseSensitive\":true,\"Name\":\"category\"},{\"TypeName\":\"VARCHAR\",\"IsCaseSensitive\":true,\"Name\":\"primary_ind\"}]}","","","",null,null,98,0,17]]}} 